{"segments":[{"start":4.462,"end":28.304,"text":"弟兄姊妹平安，我們一起來思想是篇一百一十九篇，八十一節到九十六節，來思想這首字母詩的第十一個字母，跟第十二個字母，第十一個字母是Kav，八十一節我心可想你的救恩，原文還要再加上以至衰竭，所以是我心可想你的救恩，以至衰竭，仰望你的應許。","words":[{"word":"弟","start":4.462,"end":4.622,"score":0.003},{"word":"兄","start":4.622,"end":4.742,"score":0},{"word":"姊","start":4.742,"end":4.842,"score":0},{"word":"妹","start":4.842,"end":4.982,"score":0.001},{"word":"平","start":4.982,"end":5.143,"score":0.067},{"word":"安","start":5.143,"end":5.523,"score":0.026},{"word":"，"},{"word":"我","start":5.523,"end":5.583,"score":0},{"word":"們","start":5.583,"end":5.603,"score":0.001},{"word":"一","start":5.603,"end":5.723,"score":0},{"word":"起","start":5.723,"end":5.783,"score":0.002},{"word":"來","start":5.783,"end":5.923,"score":0},{"word":"思","start":5.923,"end":6.124,"score":0},{"word":"想","start":6.124,"end":6.344,"score":0.004},{"word":"是","start":6.344,"end":6.524,"score":0.01},{"word":"篇","start":6.524,"end":6.664,"score":0.002},{"word":"一","start":6.664,"end":6.864,"score":0},{"word":"百","start":6.864,"end":7.004,"score":0.111},{"word":"一","start":7.004,"end":7.104,"score":0.187},{"word":"十","start":7.104,"end":7.305,"score":0.011},{"word":"九","start":7.305,"end":7.525,"score":0.044},{"word":"篇","start":7.525,"end":7.905,"score":0.001},{"word":"，"},{"word":"八","start":7.905,"end":8.085,"score":0.088},{"word":"十","start":8.085,"end":8.246,"score":0.011},{"word":"一","start":8.246,"end":8.506,"score":0.003},{"word":"節","start":8.506,"end":8.686,"score":0},{"word":"到","start":8.686,"end":8.946,"score":0.072},{"word":"九","start":8.946,"end":8.966,"score":0.016},{"word":"十","start":8.966,"end":9.267,"score":0.001},{"word":"六","start":9.267,"end":9.627,"score":0.004},{"word":"節","start":9.627,"end":10.227,"score":0},{"word":"，"},{"word":"來","start":10.227,"end":10.448,"score":0.09},{"word":"思","start":10.448,"end":10.668,"score":0.001},{"word":"想","start":10.668,"end":10.828,"score":0.003},{"word":"這","start":10.828,"end":11.068,"score":0.004},{"word":"首","start":11.068,"end":11.228,"score":0.016},{"word":"字","start":11.228,"end":11.489,"score":0.001},{"word":"母","start":11.489,"end":11.709,"score":0},{"word":"詩","start":11.709,"end":11.869,"score":0},{"word":"的","start":11.869,"end":12.069,"score":0.093},{"word":"第","start":12.069,"end":12.249,"score":0.033},{"word":"十","start":12.249,"end":12.55,"score":0},{"word":"一","start":12.55,"end":12.65,"score":0.197},{"word":"個","start":12.65,"end":12.83,"score":0.071},{"word":"字","start":12.83,"end":13.07,"score":0.004},{"word":"母","start":13.07,"end":13.29,"score":0},{"word":"，"},{"word":"跟","start":13.29,"end":13.571,"score":0},{"word":"第","start":13.571,"end":13.691,"score":0},{"word":"十","start":13.691,"end":13.771,"score":0.001},{"word":"二","start":13.771,"end":13.931,"score":0.003},{"word":"個","start":13.931,"end":14.091,"score":0.117},{"word":"字","start":14.091,"end":14.251,"score":0.003},{"word":"母","start":14.251,"end":14.832,"score":0.001},{"word":"，"},{"word":"第","start":14.832,"end":15.072,"score":0.039},{"word":"十","start":15.072,"end":15.132,"score":0},{"word":"一","start":15.132,"end":15.212,"score":0.24},{"word":"個","start":15.212,"end":15.372,"score":0.121},{"word":"字","start":15.372,"end":15.532,"score":0.005},{"word":"母","start":15.532,"end":15.632,"score":0},{"word":"是","start":15.632,"end":16.874,"score":0.003},{"word":"K"},{"word":"a"},{"word":"v"},{"word":"，"},{"word":"八","start":16.874,"end":17.034,"score":0.089},{"word":"十","start":17.034,"end":17.154,"score":0.046},{"word":"一","start":17.154,"end":17.294,"score":0.142},{"word":"節","start":17.294,"end":17.634,"score":0.002},{"word":"我","start":17.634,"end":18.435,"score":0},{"word":"心","start":18.435,"end":18.455,"score":0.064},{"word":"可","start":18.455,"end":18.495,"score":0},{"word":"想","start":18.495,"end":18.675,"score":0.001},{"word":"你","start":18.675,"end":18.795,"score":0.007},{"word":"的","start":18.795,"end":19.036,"score":0.067},{"word":"救","start":19.036,"end":19.216,"score":0.005},{"word":"恩","start":19.216,"end":19.856,"score":0.001},{"word":"，"},{"word":"原","start":19.856,"end":20.037,"score":0.041},{"word":"文","start":20.037,"end":20.417,"score":0.032},{"word":"還","start":20.417,"end":20.597,"score":0.019},{"word":"要","start":20.597,"end":20.697,"score":0.001},{"word":"再","start":20.697,"end":20.877,"score":0},{"word":"加","start":20.877,"end":21.118,"score":0},{"word":"上","start":21.118,"end":21.378,"score":0.066},{"word":"以","start":21.378,"end":21.698,"score":0.004},{"word":"至","start":21.698,"end":22.179,"score":0.001},{"word":"衰","start":22.179,"end":23.36,"score":0},{"word":"竭"},{"word":"，"},{"word":"所","start":23.36,"end":23.46,"score":0.001},{"word":"以","start":23.46,"end":23.6,"score":0.058},{"word":"是","start":23.6,"end":23.92,"score":0.006},{"word":"我","start":23.92,"end":24.12,"score":0.057},{"word":"心","start":24.12,"end":24.361,"score":0.03},{"word":"可","start":24.361,"end":24.641,"score":0.038},{"word":"想","start":24.641,"end":24.801,"score":0.001},{"word":"你","start":24.801,"end":24.901,"score":0.051},{"word":"的","start":24.901,"end":25.141,"score":0.004},{"word":"救","start":25.141,"end":25.262,"score":0},{"word":"恩","start":25.262,"end":25.522,"score":0},{"word":"，"},{"word":"以","start":25.522,"end":25.742,"score":0.008},{"word":"至","start":25.742,"end":26.062,"score":0.001},{"word":"衰","start":26.062,"end":26.363,"score":0},{"word":"竭"},{"word":"，"},{"word":"仰","start":26.363,"end":27.544,"score":0},{"word":"望","start":27.544,"end":27.704,"score":0.037},{"word":"你","start":27.704,"end":27.804,"score":0.096},{"word":"的","start":27.804,"end":27.964,"score":0.125},{"word":"應","start":27.964,"end":28.284,"score":0.017},{"word":"許","start":28.284,"end":28.304,"score":0.171},{"word":"。"}]},{"start":28.985,"end":48.479,"text":"這一節裡面第一個字就是衰竭。所以衰竭也是接下來這八節經文的關鍵字。衰竭就是精疲力竭。世人說他僅僅抓住神的應許。神救恩的話語僅僅抓住。因為神的話語可以救他活命。","words":[{"word":"這","start":28.985,"end":29.525,"score":0},{"word":"一","start":29.525,"end":29.726,"score":0.098},{"word":"節","start":29.726,"end":29.826,"score":0.01},{"word":"裡","start":29.826,"end":30.046,"score":0.024},{"word":"面","start":30.046,"end":30.326,"score":0.067},{"word":"第","start":30.326,"end":30.486,"score":0.005},{"word":"一","start":30.486,"end":30.566,"score":0.049},{"word":"個","start":30.566,"end":30.766,"score":0.072},{"word":"字","start":30.766,"end":31.147,"score":0.003},{"word":"就","start":31.147,"end":31.567,"score":0.037},{"word":"是","start":31.567,"end":32.007,"score":0.002},{"word":"衰","start":32.007,"end":32.768,"score":0},{"word":"竭"},{"word":"。"},{"word":"所","start":32.768,"end":33.128,"score":0},{"word":"以","start":33.128,"end":33.268,"score":0},{"word":"衰","start":33.268,"end":33.488,"score":0},{"word":"竭"},{"word":"也","start":33.488,"end":33.628,"score":0.024},{"word":"是","start":33.628,"end":33.888,"score":0.011},{"word":"接","start":33.888,"end":34.049,"score":0},{"word":"下","start":34.049,"end":34.109,"score":0.002},{"word":"來","start":34.109,"end":34.229,"score":0},{"word":"這","start":34.229,"end":34.409,"score":0},{"word":"八","start":34.409,"end":34.689,"score":0},{"word":"節","start":34.689,"end":35.169,"score":0},{"word":"經","start":35.169,"end":35.329,"score":0.032},{"word":"文","start":35.329,"end":35.55,"score":0},{"word":"的","start":35.55,"end":35.89,"score":0},{"word":"關","start":35.89,"end":36.07,"score":0},{"word":"鍵","start":36.07,"end":36.33,"score":0.001},{"word":"字","start":36.33,"end":37.191,"score":0.005},{"word":"。"},{"word":"衰","start":37.191,"end":37.551,"score":0},{"word":"竭"},{"word":"就","start":37.551,"end":37.671,"score":0.166},{"word":"是","start":37.671,"end":37.891,"score":0.09},{"word":"精","start":37.891,"end":38.171,"score":0.003},{"word":"疲","start":38.171,"end":38.732,"score":0},{"word":"力","start":38.732,"end":39.292,"score":0},{"word":"竭"},{"word":"。"},{"word":"世","start":39.292,"end":39.432,"score":0.013},{"word":"人","start":39.432,"end":39.652,"score":0.058},{"word":"說","start":39.652,"end":39.773,"score":0.005},{"word":"他","start":39.773,"end":39.913,"score":0.077},{"word":"僅","start":39.913,"end":40.153,"score":0},{"word":"僅","start":40.153,"end":40.353,"score":0.002},{"word":"抓","start":40.353,"end":40.733,"score":0},{"word":"住","start":40.733,"end":41.053,"score":0},{"word":"神","start":41.053,"end":41.454,"score":0.002},{"word":"的","start":41.454,"end":41.794,"score":0.058},{"word":"應","start":41.794,"end":42.194,"score":0.021},{"word":"許","start":42.194,"end":42.855,"score":0.012},{"word":"。"},{"word":"神","start":42.855,"end":43.275,"score":0.004},{"word":"救","start":43.275,"end":43.375,"score":0},{"word":"恩","start":43.375,"end":43.535,"score":0},{"word":"的","start":43.535,"end":43.855,"score":0.059},{"word":"話","start":43.855,"end":43.995,"score":0.028},{"word":"語","start":43.995,"end":44.276,"score":0},{"word":"僅","start":44.276,"end":44.956,"score":0},{"word":"僅","start":44.956,"end":45.136,"score":0},{"word":"抓","start":45.136,"end":45.436,"score":0},{"word":"住","start":45.436,"end":45.997,"score":0},{"word":"。"},{"word":"因","start":45.997,"end":46.157,"score":0.045},{"word":"為","start":46.157,"end":46.277,"score":0.105},{"word":"神","start":46.277,"end":46.417,"score":0.011},{"word":"的","start":46.417,"end":46.737,"score":0.028},{"word":"話","start":46.737,"end":46.878,"score":0},{"word":"語","start":46.878,"end":47.238,"score":0.005},{"word":"可","start":47.238,"end":47.378,"score":0.092},{"word":"以","start":47.378,"end":47.678,"score":0.001},{"word":"救","start":47.678,"end":47.858,"score":0.009},{"word":"他","start":47.858,"end":48.258,"score":0.024},{"word":"活","start":48.258,"end":48.459,"score":0.071},{"word":"命","start":48.459,"end":48.479,"score":0.767},{"word":"。"}]},{"start":49.019,"end":68.326,"text":"神的話語就像一根繩子,詩人緊緊抓住祂,筋疲力竭,耗盡力氣,也要死命的抓住祂。為什麼呢?待會我們會看見,原來有另外一股力量,也拼死命的要把詩人拖下去,讓祂滅亡。82節","words":[{"word":"神","start":49.019,"end":49.359,"score":0.002},{"word":"的","start":49.359,"end":49.559,"score":0.061},{"word":"話","start":49.559,"end":49.739,"score":0.039},{"word":"語","start":49.739,"end":49.879,"score":0.008},{"word":"就","start":49.879,"end":50.039,"score":0.117},{"word":"像","start":50.039,"end":50.179,"score":0.012},{"word":"一","start":50.179,"end":50.259,"score":0.004},{"word":"根","start":50.259,"end":50.52,"score":0},{"word":"繩","start":50.52,"end":50.58,"score":0},{"word":"子","start":50.58,"end":50.84,"score":0},{"word":","},{"word":"詩","start":50.84,"end":51.52,"score":0},{"word":"人","start":51.52,"end":51.7,"score":0.068},{"word":"緊","start":51.7,"end":52.06,"score":0},{"word":"緊","start":52.06,"end":52.24,"score":0},{"word":"抓","start":52.24,"end":52.52,"score":0},{"word":"住","start":52.52,"end":53.721,"score":0},{"word":"祂"},{"word":","},{"word":"筋","start":53.721,"end":54.281,"score":0},{"word":"疲","start":54.281,"end":54.441,"score":0},{"word":"力","start":54.441,"end":54.901,"score":0},{"word":"竭"},{"word":","},{"word":"耗","start":54.901,"end":55.301,"score":0},{"word":"盡","start":55.301,"end":55.562,"score":0.008},{"word":"力","start":55.562,"end":55.842,"score":0.035},{"word":"氣","start":55.842,"end":56.242,"score":0.001},{"word":","},{"word":"也","start":56.242,"end":56.422,"score":0.039},{"word":"要","start":56.422,"end":56.882,"score":0.042},{"word":"死","start":56.882,"end":57.222,"score":0.012},{"word":"命","start":57.222,"end":57.362,"score":0.086},{"word":"的","start":57.362,"end":57.582,"score":0.083},{"word":"抓","start":57.582,"end":57.722,"score":0},{"word":"住","start":57.722,"end":58.663,"score":0},{"word":"祂"},{"word":"。"},{"word":"為","start":58.663,"end":58.843,"score":0.022},{"word":"什","start":58.843,"end":58.983,"score":0.139},{"word":"麼","start":58.983,"end":59.123,"score":0.142},{"word":"呢","start":59.123,"end":59.663,"score":0.007},{"word":"?"},{"word":"待","start":59.663,"end":59.803,"score":0.001},{"word":"會","start":59.803,"end":59.903,"score":0.012},{"word":"我","start":59.903,"end":60.043,"score":0.029},{"word":"們","start":60.043,"end":60.123,"score":0},{"word":"會","start":60.123,"end":60.263,"score":0.129},{"word":"看","start":60.263,"end":60.563,"score":0.059},{"word":"見","start":60.563,"end":61.104,"score":0},{"word":","},{"word":"原","start":61.104,"end":61.204,"score":0.095},{"word":"來","start":61.204,"end":61.324,"score":0.014},{"word":"有","start":61.324,"end":61.544,"score":0.087},{"word":"另","start":61.544,"end":61.764,"score":0.049},{"word":"外","start":61.764,"end":61.884,"score":0.124},{"word":"一","start":61.884,"end":62.024,"score":0.126},{"word":"股","start":62.024,"end":62.184,"score":0.012},{"word":"力","start":62.184,"end":62.404,"score":0.06},{"word":"量","start":62.404,"end":62.964,"score":0.033},{"word":","},{"word":"也","start":62.964,"end":63.265,"score":0.051},{"word":"拼","start":63.265,"end":63.705,"score":0.001},{"word":"死","start":63.705,"end":63.905,"score":0.03},{"word":"命","start":63.905,"end":64.105,"score":0.062},{"word":"的","start":64.105,"end":64.665,"score":0},{"word":"要","start":64.665,"end":64.885,"score":0.087},{"word":"把","start":64.885,"end":65.305,"score":0.003},{"word":"詩","start":65.305,"end":65.485,"score":0},{"word":"人","start":65.485,"end":65.806,"score":0.053},{"word":"拖","start":65.806,"end":66.106,"score":0},{"word":"下","start":66.106,"end":66.366,"score":0},{"word":"去","start":66.366,"end":66.906,"score":0},{"word":","},{"word":"讓","start":66.906,"end":67.086,"score":0.102},{"word":"祂"},{"word":"滅","start":67.086,"end":67.546,"score":0},{"word":"亡","start":67.546,"end":68.306,"score":0},{"word":"。"},{"word":"8"},{"word":"2"},{"word":"節","start":68.306,"end":68.326,"score":0}]},{"start":70.503,"end":92.855,"text":"我因盼望你的應許,眼睛失明,說,你何時安慰我?我好像煙燻的皮帶,卻不忘記你的綠綠。詩人筋疲力竭,死命抓住神的話,以至於仰望神的救恩望眼欲穿,以至於常流淚呼求主名,眼睛幾乎失明。","words":[{"word":"我","start":70.503,"end":70.703,"score":0.099},{"word":"因","start":70.703,"end":70.923,"score":0.007},{"word":"盼","start":70.923,"end":71.183,"score":0},{"word":"望","start":71.183,"end":71.303,"score":0.05},{"word":"你","start":71.303,"end":71.383,"score":0},{"word":"的","start":71.383,"end":71.504,"score":0.117},{"word":"應","start":71.504,"end":71.804,"score":0.021},{"word":"許","start":71.804,"end":72.164,"score":0.001},{"word":","},{"word":"眼","start":72.164,"end":72.404,"score":0.004},{"word":"睛","start":72.404,"end":72.664,"score":0.001},{"word":"失","start":72.664,"end":72.904,"score":0.001},{"word":"明","start":72.904,"end":73.445,"score":0},{"word":","},{"word":"說","start":73.445,"end":74.085,"score":0.007},{"word":","},{"word":"你","start":74.085,"end":74.345,"score":0.01},{"word":"何","start":74.345,"end":74.545,"score":0.009},{"word":"時","start":74.545,"end":74.885,"score":0.006},{"word":"安","start":74.885,"end":75.145,"score":0.022},{"word":"慰","start":75.145,"end":75.466,"score":0.002},{"word":"我","start":75.466,"end":76.046,"score":0},{"word":"?"},{"word":"我","start":76.046,"end":76.186,"score":0.051},{"word":"好","start":76.186,"end":76.486,"score":0.064},{"word":"像","start":76.486,"end":76.746,"score":0.001},{"word":"煙","start":76.746,"end":77.226,"score":0},{"word":"燻"},{"word":"的","start":77.226,"end":77.387,"score":0.124},{"word":"皮","start":77.387,"end":77.647,"score":0},{"word":"帶","start":77.647,"end":78.427,"score":0.002},{"word":","},{"word":"卻","start":78.427,"end":78.687,"score":0.01},{"word":"不","start":78.687,"end":78.867,"score":0.107},{"word":"忘","start":78.867,"end":79.127,"score":0.029},{"word":"記","start":79.127,"end":79.368,"score":0},{"word":"你","start":79.368,"end":79.528,"score":0},{"word":"的","start":79.528,"end":79.668,"score":0.141},{"word":"綠","start":79.668,"end":79.908,"score":0},{"word":"綠","start":79.908,"end":80.788,"score":0},{"word":"。"},{"word":"詩","start":80.788,"end":80.968,"score":0},{"word":"人","start":80.968,"end":81.829,"score":0.003},{"word":"筋","start":81.829,"end":82.209,"score":0},{"word":"疲","start":82.209,"end":82.389,"score":0},{"word":"力","start":82.389,"end":82.829,"score":0},{"word":"竭"},{"word":","},{"word":"死","start":82.829,"end":83.01,"score":0.037},{"word":"命","start":83.01,"end":83.27,"score":0.01},{"word":"抓","start":83.27,"end":83.49,"score":0},{"word":"住","start":83.49,"end":83.67,"score":0},{"word":"神","start":83.67,"end":83.79,"score":0.007},{"word":"的","start":83.79,"end":84.01,"score":0.013},{"word":"話","start":84.01,"end":84.59,"score":0.004},{"word":","},{"word":"以","start":84.59,"end":84.79,"score":0.026},{"word":"至","start":84.79,"end":84.971,"score":0.005},{"word":"於","start":84.971,"end":85.471,"score":0},{"word":"仰","start":85.471,"end":85.671,"score":0.002},{"word":"望","start":85.671,"end":85.851,"score":0},{"word":"神","start":85.851,"end":86.031,"score":0.016},{"word":"的","start":86.031,"end":86.231,"score":0.006},{"word":"救","start":86.231,"end":86.391,"score":0.006},{"word":"恩","start":86.391,"end":86.872,"score":0.001},{"word":"望","start":86.872,"end":87.152,"score":0.017},{"word":"眼","start":87.152,"end":87.752,"score":0.004},{"word":"欲","start":87.752,"end":87.772,"score":0},{"word":"穿","start":87.772,"end":88.432,"score":0},{"word":","},{"word":"以","start":88.432,"end":88.612,"score":0.034},{"word":"至","start":88.612,"end":88.773,"score":0},{"word":"於","start":88.773,"end":89.313,"score":0.024},{"word":"常","start":89.313,"end":89.693,"score":0},{"word":"流","start":89.693,"end":89.933,"score":0.045},{"word":"淚","start":89.933,"end":90.293,"score":0},{"word":"呼","start":90.293,"end":90.433,"score":0},{"word":"求","start":90.433,"end":90.694,"score":0.035},{"word":"主","start":90.694,"end":90.934,"score":0},{"word":"名","start":90.934,"end":91.574,"score":0.004},{"word":","},{"word":"眼","start":91.574,"end":91.814,"score":0.009},{"word":"睛","start":91.814,"end":91.834,"score":0},{"word":"幾","start":91.834,"end":92.314,"score":0},{"word":"乎","start":92.314,"end":92.615,"score":0.004},{"word":"失","start":92.615,"end":92.835,"score":0.003},{"word":"明","start":92.835,"end":92.855,"score":0.367},{"word":"。"}]},{"start":93.575,"end":108.99,"text":"身心靈衰竭耗盡,好像被煙燻過的皮帶,乾乾癟癟的,失去了彈性,失去了活力。但他仍然不忘記神的話語,繼續仰望神,抓緊神的話。","words":[{"word":"身","start":93.575,"end":94.055,"score":0.024},{"word":"心","start":94.055,"end":94.296,"score":0.034},{"word":"靈","start":94.296,"end":94.856,"score":0.003},{"word":"衰","start":94.856,"end":95.417,"score":0},{"word":"竭"},{"word":"耗","start":95.417,"end":95.817,"score":0},{"word":"盡","start":95.817,"end":96.378,"score":0.003},{"word":","},{"word":"好","start":96.378,"end":96.638,"score":0.057},{"word":"像","start":96.638,"end":96.838,"score":0.05},{"word":"被","start":96.838,"end":97.158,"score":0.048},{"word":"煙","start":97.158,"end":97.799,"score":0.001},{"word":"燻"},{"word":"過","start":97.799,"end":97.939,"score":0.131},{"word":"的","start":97.939,"end":98.179,"score":0.08},{"word":"皮","start":98.179,"end":98.48,"score":0.001},{"word":"帶","start":98.48,"end":99.261,"score":0.002},{"word":","},{"word":"乾","start":99.261,"end":99.821,"score":0.001},{"word":"乾","start":99.821,"end":100.001,"score":0},{"word":"癟"},{"word":"癟"},{"word":"的","start":100.001,"end":100.542,"score":0.002},{"word":","},{"word":"失","start":100.542,"end":100.742,"score":0.001},{"word":"去","start":100.742,"end":100.882,"score":0.051},{"word":"了","start":100.882,"end":101.022,"score":0.009},{"word":"彈","start":101.022,"end":101.343,"score":0.001},{"word":"性","start":101.343,"end":101.643,"score":0.026},{"word":","},{"word":"失","start":101.643,"end":101.823,"score":0},{"word":"去","start":101.823,"end":101.923,"score":0.01},{"word":"了","start":101.923,"end":102.203,"score":0},{"word":"活","start":102.203,"end":102.343,"score":0},{"word":"力","start":102.343,"end":103.485,"score":0},{"word":"。"},{"word":"但","start":103.485,"end":103.605,"score":0.131},{"word":"他","start":103.605,"end":103.785,"score":0.078},{"word":"仍","start":103.785,"end":103.985,"score":0.005},{"word":"然","start":103.985,"end":104.405,"score":0.039},{"word":"不","start":104.405,"end":104.546,"score":0.141},{"word":"忘","start":104.546,"end":104.826,"score":0.004},{"word":"記","start":104.826,"end":105.246,"score":0.001},{"word":"神","start":105.246,"end":105.527,"score":0.003},{"word":"的","start":105.527,"end":105.947,"score":0.027},{"word":"話","start":105.947,"end":106.087,"score":0.012},{"word":"語","start":106.087,"end":106.748,"score":0.002},{"word":","},{"word":"繼","start":106.748,"end":106.988,"score":0.001},{"word":"續","start":106.988,"end":107.228,"score":0},{"word":"仰","start":107.228,"end":107.488,"score":0.001},{"word":"望","start":107.488,"end":107.809,"score":0.012},{"word":"神","start":107.809,"end":108.189,"score":0.005},{"word":","},{"word":"抓","start":108.189,"end":108.349,"score":0},{"word":"緊","start":108.349,"end":108.61,"score":0.002},{"word":"神","start":108.61,"end":108.75,"score":0.04},{"word":"的","start":108.75,"end":108.97,"score":0.037},{"word":"話","start":108.97,"end":108.99,"score":0.484},{"word":"。"}]},{"start":110.384,"end":136.766,"text":"八十四節,你仆人的年日有多少呢?你幾時向逼迫我的人施行審判呢?所以答案出來了。另外一股力量,就是仇敵在拉扯、逼迫他的生命。你不從你律法的驕傲人為我掘了坑。你的命令盡都誠實,但他們卻無理的逼迫我,求你幫助我。","words":[{"word":"八","start":110.384,"end":110.544,"score":0.019},{"word":"十","start":110.544,"end":110.704,"score":0},{"word":"四","start":110.704,"end":110.944,"score":0.009},{"word":"節","start":110.944,"end":111.165,"score":0.026},{"word":","},{"word":"你","start":111.165,"end":111.545,"score":0.048},{"word":"仆","start":111.545,"end":111.665,"score":0},{"word":"人","start":111.665,"end":111.825,"score":0.05},{"word":"的","start":111.825,"end":111.865,"score":0.001},{"word":"年","start":111.865,"end":112.045,"score":0},{"word":"日","start":112.045,"end":112.266,"score":0.07},{"word":"有","start":112.266,"end":112.506,"score":0.079},{"word":"多","start":112.506,"end":112.726,"score":0.089},{"word":"少","start":112.726,"end":112.986,"score":0.028},{"word":"呢","start":112.986,"end":114.087,"score":0},{"word":"?"},{"word":"你","start":114.087,"end":114.307,"score":0.084},{"word":"幾","start":114.307,"end":114.608,"score":0.044},{"word":"時","start":114.608,"end":115.008,"score":0.003},{"word":"向","start":115.008,"end":115.348,"score":0.012},{"word":"逼","start":115.348,"end":115.688,"score":0.002},{"word":"迫","start":115.688,"end":115.929,"score":0.001},{"word":"我","start":115.929,"end":116.069,"score":0},{"word":"的","start":116.069,"end":116.209,"score":0},{"word":"人","start":116.209,"end":116.509,"score":0.065},{"word":"施","start":116.509,"end":116.689,"score":0},{"word":"行","start":116.689,"end":116.889,"score":0.032},{"word":"審","start":116.889,"end":117.11,"score":0.002},{"word":"判","start":117.11,"end":117.35,"score":0.003},{"word":"呢","start":117.35,"end":118.231,"score":0},{"word":"?"},{"word":"所","start":118.231,"end":118.351,"score":0.001},{"word":"以","start":118.351,"end":118.491,"score":0.002},{"word":"答","start":118.491,"end":118.611,"score":0.002},{"word":"案","start":118.611,"end":118.811,"score":0},{"word":"出","start":118.811,"end":118.931,"score":0},{"word":"來","start":118.931,"end":119.151,"score":0.031},{"word":"了","start":119.151,"end":119.532,"score":0},{"word":"。"},{"word":"另","start":119.532,"end":119.692,"score":0.006},{"word":"外","start":119.692,"end":119.752,"score":0.087},{"word":"一","start":119.752,"end":119.852,"score":0},{"word":"股","start":119.852,"end":119.992,"score":0},{"word":"力","start":119.992,"end":120.212,"score":0.008},{"word":"量","start":120.212,"end":120.813,"score":0.017},{"word":","},{"word":"就","start":120.813,"end":120.953,"score":0.024},{"word":"是","start":120.953,"end":121.253,"score":0.002},{"word":"仇","start":121.253,"end":121.593,"score":0},{"word":"敵","start":121.593,"end":122.034,"score":0},{"word":"在","start":122.034,"end":122.354,"score":0},{"word":"拉","start":122.354,"end":123.075,"score":0},{"word":"扯","start":123.075,"end":123.355,"score":0},{"word":"、"},{"word":"逼","start":123.355,"end":123.635,"score":0.001},{"word":"迫","start":123.635,"end":123.735,"score":0},{"word":"他","start":123.735,"end":123.855,"score":0.146},{"word":"的","start":123.855,"end":124.055,"score":0.083},{"word":"生","start":124.055,"end":124.256,"score":0},{"word":"命","start":124.256,"end":125.396,"score":0.001},{"word":"。"},{"word":"你","start":125.396,"end":126.137,"score":0},{"word":"不","start":126.137,"end":126.377,"score":0.083},{"word":"從","start":126.377,"end":126.637,"score":0.016},{"word":"你","start":126.637,"end":126.918,"score":0.064},{"word":"律","start":126.918,"end":127.138,"score":0.011},{"word":"法","start":127.138,"end":127.258,"score":0.113},{"word":"的","start":127.258,"end":127.478,"score":0.09},{"word":"驕","start":127.478,"end":127.618,"score":0.001},{"word":"傲","start":127.618,"end":127.859,"score":0.002},{"word":"人","start":127.859,"end":128.299,"score":0.042},{"word":"為","start":128.299,"end":128.539,"score":0.009},{"word":"我","start":128.539,"end":128.839,"score":0.065},{"word":"掘","start":128.839,"end":128.959,"score":0.001},{"word":"了","start":128.959,"end":129.18,"score":0},{"word":"坑","start":129.18,"end":130.801,"score":0.001},{"word":"。"},{"word":"你","start":130.801,"end":130.921,"score":0.16},{"word":"的","start":130.921,"end":131.101,"score":0.108},{"word":"命","start":131.101,"end":131.341,"score":0.046},{"word":"令","start":131.341,"end":131.802,"score":0.008},{"word":"盡","start":131.802,"end":132.022,"score":0.008},{"word":"都","start":132.022,"end":132.242,"score":0.088},{"word":"誠","start":132.242,"end":132.662,"score":0},{"word":"實","start":132.662,"end":133.163,"score":0},{"word":","},{"word":"但","start":133.163,"end":133.343,"score":0.07},{"word":"他","start":133.343,"end":133.543,"score":0.093},{"word":"們","start":133.543,"end":133.803,"score":0.075},{"word":"卻","start":133.803,"end":134.044,"score":0.002},{"word":"無","start":134.044,"end":134.244,"score":0.074},{"word":"理","start":134.244,"end":134.424,"score":0.004},{"word":"的","start":134.424,"end":134.644,"score":0.056},{"word":"逼","start":134.644,"end":134.804,"score":0},{"word":"迫","start":134.804,"end":135.105,"score":0.001},{"word":"我","start":135.105,"end":135.685,"score":0.034},{"word":","},{"word":"求","start":135.685,"end":135.985,"score":0.04},{"word":"你","start":135.985,"end":136.205,"score":0.012},{"word":"幫","start":136.205,"end":136.506,"score":0.061},{"word":"助","start":136.506,"end":136.746,"score":0.001},{"word":"我","start":136.746,"end":136.766,"score":0.002},{"word":"。"}]},{"start":137.483,"end":156.215,"text":"他們幾乎把我從世上滅絕,但我沒有離棄你的訓詞。求你照你的慈愛將我救活,我就遵守你口中的法度。有兩種令人好見的力量在詩人的生命中拉扯。","words":[{"word":"他","start":137.483,"end":137.663,"score":0.103},{"word":"們","start":137.663,"end":137.823,"score":0.125},{"word":"幾","start":137.823,"end":138.103,"score":0.001},{"word":"乎","start":138.103,"end":138.404,"score":0.028},{"word":"把","start":138.404,"end":138.564,"score":0.102},{"word":"我","start":138.564,"end":138.704,"score":0.079},{"word":"從","start":138.704,"end":139.004,"score":0.017},{"word":"世","start":139.004,"end":139.204,"score":0.013},{"word":"上","start":139.204,"end":139.444,"score":0.079},{"word":"滅","start":139.444,"end":139.804,"score":0.003},{"word":"絕","start":139.804,"end":140.485,"score":0.003},{"word":","},{"word":"但","start":140.485,"end":140.865,"score":0.047},{"word":"我","start":140.865,"end":141.325,"score":0.036},{"word":"沒","start":141.325,"end":141.606,"score":0.063},{"word":"有","start":141.606,"end":141.886,"score":0.071},{"word":"離","start":141.886,"end":142.286,"score":0.001},{"word":"棄","start":142.286,"end":142.586,"score":0.002},{"word":"你","start":142.586,"end":142.726,"score":0.079},{"word":"的","start":142.726,"end":142.966,"score":0.083},{"word":"訓","start":142.966,"end":143.167,"score":0.006},{"word":"詞","start":143.167,"end":144.247,"score":0.001},{"word":"。"},{"word":"求","start":144.247,"end":144.387,"score":0.063},{"word":"你","start":144.387,"end":144.627,"score":0},{"word":"照","start":144.627,"end":144.928,"score":0.006},{"word":"你","start":144.928,"end":145.068,"score":0.122},{"word":"的","start":145.068,"end":145.308,"score":0.083},{"word":"慈","start":145.308,"end":145.468,"score":0.009},{"word":"愛","start":145.468,"end":145.768,"score":0.019},{"word":"將","start":145.768,"end":145.928,"score":0},{"word":"我","start":145.928,"end":146.188,"score":0.058},{"word":"救","start":146.188,"end":146.469,"score":0.007},{"word":"活","start":146.469,"end":146.589,"score":0.064},{"word":","},{"word":"我","start":146.589,"end":147.469,"score":0.001},{"word":"就","start":147.469,"end":147.749,"score":0.03},{"word":"遵","start":147.749,"end":148.01,"score":0.001},{"word":"守","start":148.01,"end":148.21,"score":0.001},{"word":"你","start":148.21,"end":148.57,"score":0.015},{"word":"口","start":148.57,"end":148.89,"score":0.034},{"word":"中","start":148.89,"end":149.05,"score":0},{"word":"的","start":149.05,"end":149.25,"score":0.097},{"word":"法","start":149.25,"end":149.47,"score":0.04},{"word":"度","start":149.47,"end":151.392,"score":0},{"word":"。"},{"word":"有","start":151.392,"end":151.572,"score":0.104},{"word":"兩","start":151.572,"end":151.792,"score":0.042},{"word":"種","start":151.792,"end":152.032,"score":0.058},{"word":"令","start":152.032,"end":152.232,"score":0.025},{"word":"人","start":152.232,"end":152.472,"score":0.08},{"word":"好","start":152.472,"end":152.853,"score":0.012},{"word":"見","start":152.853,"end":153.093,"score":0.006},{"word":"的","start":153.093,"end":153.253,"score":0.116},{"word":"力","start":153.253,"end":153.493,"score":0},{"word":"量","start":153.493,"end":154.173,"score":0.027},{"word":"在","start":154.173,"end":154.814,"score":0.027},{"word":"詩","start":154.814,"end":154.974,"score":0},{"word":"人","start":154.974,"end":155.114,"score":0.069},{"word":"的","start":155.114,"end":155.294,"score":0},{"word":"生","start":155.294,"end":155.434,"score":0.021},{"word":"命","start":155.434,"end":155.694,"score":0.021},{"word":"中","start":155.694,"end":155.894,"score":0.004},{"word":"拉","start":155.894,"end":156.195,"score":0.001},{"word":"扯","start":156.195,"end":156.215,"score":0.005},{"word":"。"}]},{"start":157.142,"end":174.979,"text":"一個是敵人、罪惡、魔鬼、試探甚至是生命中的苦難拼命的要把他拉到坑裡面去要使他從世上滅絕但是呢,詩人緊緊抓住神的話語","words":[{"word":"一","start":157.142,"end":157.342,"score":0.093},{"word":"個","start":157.342,"end":157.562,"score":0.091},{"word":"是","start":157.562,"end":157.963,"score":0.045},{"word":"敵","start":157.963,"end":158.223,"score":0},{"word":"人","start":158.223,"end":159.144,"score":0.021},{"word":"、"},{"word":"罪","start":159.144,"end":159.404,"score":0},{"word":"惡","start":159.404,"end":160.205,"score":0.006},{"word":"、"},{"word":"魔","start":160.205,"end":160.485,"score":0.005},{"word":"鬼","start":160.485,"end":161.086,"score":0.006},{"word":"、"},{"word":"試","start":161.086,"end":161.486,"score":0},{"word":"探","start":161.486,"end":162.427,"score":0.001},{"word":"甚","start":162.427,"end":162.607,"score":0.017},{"word":"至","start":162.607,"end":162.727,"score":0.001},{"word":"是","start":162.727,"end":162.928,"score":0.004},{"word":"生","start":162.928,"end":163.068,"score":0.078},{"word":"命","start":163.068,"end":163.208,"score":0},{"word":"中","start":163.208,"end":163.328,"score":0.067},{"word":"的","start":163.328,"end":163.528,"score":0.008},{"word":"苦","start":163.528,"end":163.788,"score":0.024},{"word":"難","start":163.788,"end":164.509,"score":0},{"word":"拼","start":164.509,"end":164.689,"score":0.007},{"word":"命","start":164.689,"end":164.829,"score":0.017},{"word":"的","start":164.829,"end":164.93,"score":0.194},{"word":"要","start":164.93,"end":165.09,"score":0.018},{"word":"把","start":165.09,"end":165.23,"score":0.002},{"word":"他","start":165.23,"end":165.43,"score":0.004},{"word":"拉","start":165.43,"end":165.951,"score":0},{"word":"到","start":165.951,"end":166.531,"score":0},{"word":"坑","start":166.531,"end":166.791,"score":0.004},{"word":"裡","start":166.791,"end":166.891,"score":0.003},{"word":"面","start":166.891,"end":167.192,"score":0.009},{"word":"去","start":167.192,"end":167.832,"score":0.006},{"word":"要","start":167.832,"end":168.073,"score":0.083},{"word":"使","start":168.073,"end":168.193,"score":0.019},{"word":"他","start":168.193,"end":168.433,"score":0.063},{"word":"從","start":168.433,"end":168.793,"score":0.025},{"word":"世","start":168.793,"end":169.074,"score":0.009},{"word":"上","start":169.074,"end":169.674,"score":0.031},{"word":"滅","start":169.674,"end":170.095,"score":0.003},{"word":"絕","start":170.095,"end":171.436,"score":0.001},{"word":"但","start":171.436,"end":171.636,"score":0.074},{"word":"是","start":171.636,"end":171.816,"score":0.104},{"word":"呢","start":171.816,"end":172.217,"score":0.002},{"word":","},{"word":"詩","start":172.217,"end":172.357,"score":0},{"word":"人","start":172.357,"end":172.797,"score":0.041},{"word":"緊","start":172.797,"end":172.997,"score":0},{"word":"緊","start":172.997,"end":173.318,"score":0.004},{"word":"抓","start":173.318,"end":173.558,"score":0.017},{"word":"住","start":173.558,"end":174.339,"score":0.001},{"word":"神","start":174.339,"end":174.499,"score":0.002},{"word":"的","start":174.499,"end":174.719,"score":0.086},{"word":"話","start":174.719,"end":174.959,"score":0.02},{"word":"語","start":174.959,"end":174.979,"score":0.425}]},{"start":175.64,"end":201.099,"text":"他也是精疲力竭的抓住神的話語,死命不放。因為他相信神的話語必將他救活。我們生命中也是常常面臨這樣的一種耐力賽,這一種拉扯戰。但是我們只要抓緊神的話語,我們終必得救。這就是這八節給我們的一個提醒。雖然仰望神的話語望遠欲穿,","words":[{"word":"他","start":175.64,"end":176.08,"score":0.032},{"word":"也","start":176.08,"end":176.28,"score":0.094},{"word":"是","start":176.28,"end":176.941,"score":0.029},{"word":"精","start":176.941,"end":177.221,"score":0.008},{"word":"疲","start":177.221,"end":177.421,"score":0.001},{"word":"力","start":177.421,"end":177.782,"score":0.033},{"word":"竭"},{"word":"的","start":177.782,"end":178.002,"score":0.081},{"word":"抓","start":178.002,"end":178.182,"score":0.001},{"word":"住","start":178.182,"end":178.442,"score":0.005},{"word":"神","start":178.442,"end":178.542,"score":0},{"word":"的","start":178.542,"end":178.782,"score":0.075},{"word":"話","start":178.782,"end":178.862,"score":0.087},{"word":"語","start":178.862,"end":179.463,"score":0},{"word":","},{"word":"死","start":179.463,"end":179.723,"score":0.005},{"word":"命","start":179.723,"end":179.943,"score":0.024},{"word":"不","start":179.943,"end":180.163,"score":0.073},{"word":"放","start":180.163,"end":180.364,"score":0},{"word":"。"},{"word":"因","start":180.364,"end":180.424,"score":0},{"word":"為","start":180.424,"end":180.944,"score":0},{"word":"他","start":180.944,"end":181.124,"score":0},{"word":"相","start":181.124,"end":181.144,"score":0.001},{"word":"信","start":181.144,"end":181.484,"score":0},{"word":"神","start":181.484,"end":181.625,"score":0.002},{"word":"的","start":181.625,"end":181.865,"score":0},{"word":"話","start":181.865,"end":182.045,"score":0.023},{"word":"語","start":182.045,"end":182.605,"score":0.003},{"word":"必","start":182.605,"end":182.805,"score":0.052},{"word":"將","start":182.805,"end":182.946,"score":0.008},{"word":"他","start":182.946,"end":183.166,"score":0},{"word":"救","start":183.166,"end":183.386,"score":0.001},{"word":"活","start":183.386,"end":184.227,"score":0},{"word":"。"},{"word":"我","start":184.227,"end":184.327,"score":0.198},{"word":"們","start":184.327,"end":184.447,"score":0.166},{"word":"生","start":184.447,"end":184.547,"score":0.087},{"word":"命","start":184.547,"end":184.767,"score":0.017},{"word":"中","start":184.767,"end":184.947,"score":0.092},{"word":"也","start":184.947,"end":185.107,"score":0.11},{"word":"是","start":185.107,"end":185.447,"score":0.018},{"word":"常","start":185.447,"end":185.468,"score":0},{"word":"常","start":185.468,"end":185.708,"score":0.005},{"word":"面","start":185.708,"end":185.848,"score":0.131},{"word":"臨","start":185.848,"end":186.048,"score":0},{"word":"這","start":186.048,"end":186.148,"score":0.001},{"word":"樣","start":186.148,"end":186.288,"score":0.008},{"word":"的","start":186.288,"end":186.428,"score":0.037},{"word":"一","start":186.428,"end":186.568,"score":0},{"word":"種","start":186.568,"end":186.869,"score":0},{"word":"耐","start":186.869,"end":187.149,"score":0},{"word":"力","start":187.149,"end":187.449,"score":0.002},{"word":"賽","start":187.449,"end":188.09,"score":0},{"word":","},{"word":"這","start":188.09,"end":188.21,"score":0.037},{"word":"一","start":188.21,"end":188.31,"score":0.002},{"word":"種","start":188.31,"end":188.61,"score":0.029},{"word":"拉","start":188.61,"end":188.91,"score":0.015},{"word":"扯","start":188.91,"end":189.23,"score":0},{"word":"戰","start":189.23,"end":190.311,"score":0},{"word":"。"},{"word":"但","start":190.311,"end":190.491,"score":0.069},{"word":"是","start":190.491,"end":190.692,"score":0.066},{"word":"我","start":190.692,"end":190.832,"score":0},{"word":"們","start":190.832,"end":190.972,"score":0},{"word":"只","start":190.972,"end":191.032,"score":0},{"word":"要","start":191.032,"end":191.612,"score":0.013},{"word":"抓","start":191.612,"end":191.993,"score":0},{"word":"緊","start":191.993,"end":192.213,"score":0.005},{"word":"神","start":192.213,"end":192.373,"score":0.007},{"word":"的","start":192.373,"end":192.593,"score":0},{"word":"話","start":192.593,"end":192.693,"score":0},{"word":"語","start":192.693,"end":193.314,"score":0},{"word":","},{"word":"我","start":193.314,"end":193.394,"score":0.106},{"word":"們","start":193.394,"end":193.494,"score":0.191},{"word":"終","start":193.494,"end":193.754,"score":0},{"word":"必","start":193.754,"end":193.874,"score":0},{"word":"得","start":193.874,"end":194.154,"score":0.002},{"word":"救","start":194.154,"end":194.755,"score":0},{"word":"。"},{"word":"這","start":194.755,"end":194.875,"score":0.162},{"word":"就","start":194.875,"end":195.055,"score":0.109},{"word":"是","start":195.055,"end":195.295,"score":0.053},{"word":"這","start":195.295,"end":195.695,"score":0.03},{"word":"八","start":195.695,"end":195.835,"score":0},{"word":"節","start":195.835,"end":196.396,"score":0},{"word":"給","start":196.396,"end":196.536,"score":0.14},{"word":"我","start":196.536,"end":196.636,"score":0.06},{"word":"們","start":196.636,"end":196.736,"score":0.002},{"word":"的","start":196.736,"end":196.916,"score":0.111},{"word":"一","start":196.916,"end":197.076,"score":0.025},{"word":"個","start":197.076,"end":197.297,"score":0.081},{"word":"提","start":197.297,"end":197.577,"score":0.049},{"word":"醒","start":197.577,"end":198.317,"score":0.002},{"word":"。"},{"word":"雖","start":198.317,"end":198.497,"score":0.063},{"word":"然","start":198.497,"end":199.178,"score":0.028},{"word":"仰","start":199.178,"end":199.378,"score":0.001},{"word":"望","start":199.378,"end":199.518,"score":0.055},{"word":"神","start":199.518,"end":199.678,"score":0.003},{"word":"的","start":199.678,"end":199.919,"score":0.042},{"word":"話","start":199.919,"end":200.059,"score":0.007},{"word":"語","start":200.059,"end":200.359,"score":0.008},{"word":"望","start":200.359,"end":200.639,"score":0.001},{"word":"遠","start":200.639,"end":200.799,"score":0},{"word":"欲","start":200.799,"end":201.079,"score":0.001},{"word":"穿","start":201.079,"end":201.099,"score":0.032},{"word":","}]},{"start":201.8,"end":229.593,"text":"令人身心疲憊,但是不要放棄。忍耐到底,仰望神的人,終必得救,不致羞愧。我們來看一下第二段,89節到96節,是第12個字母Lamed。89節,耶和華啊,你的話安定在天,直到永遠。第89節的第一個字母原文是直到永遠,所以它也是接下來8節的關鍵字。","words":[{"word":"令","start":201.8,"end":202.14,"score":0.006},{"word":"人","start":202.14,"end":202.42,"score":0.066},{"word":"身","start":202.42,"end":202.78,"score":0.013},{"word":"心","start":202.78,"end":203.301,"score":0.001},{"word":"疲","start":203.301,"end":203.541,"score":0},{"word":"憊","start":203.541,"end":204.201,"score":0},{"word":","},{"word":"但","start":204.201,"end":204.401,"score":0.002},{"word":"是","start":204.401,"end":204.701,"score":0.001},{"word":"不","start":204.701,"end":204.761,"score":0.001},{"word":"要","start":204.761,"end":204.781,"score":0.01},{"word":"放","start":204.781,"end":205.242,"score":0},{"word":"棄","start":205.242,"end":205.942,"score":0},{"word":"。"},{"word":"忍","start":205.942,"end":206.082,"score":0},{"word":"耐","start":206.082,"end":206.302,"score":0},{"word":"到","start":206.302,"end":206.522,"score":0},{"word":"底","start":206.522,"end":206.542,"score":0.028},{"word":","},{"word":"仰","start":206.542,"end":206.942,"score":0},{"word":"望","start":206.942,"end":207.142,"score":0},{"word":"神","start":207.142,"end":207.283,"score":0},{"word":"的","start":207.283,"end":207.303,"score":0.003},{"word":"人","start":207.303,"end":207.803,"score":0.038},{"word":","},{"word":"終","start":207.803,"end":208.143,"score":0.002},{"word":"必","start":208.143,"end":208.283,"score":0},{"word":"得","start":208.283,"end":208.583,"score":0.012},{"word":"救","start":208.583,"end":209.023,"score":0},{"word":","},{"word":"不","start":209.023,"end":209.163,"score":0.137},{"word":"致","start":209.163,"end":209.424,"score":0.001},{"word":"羞","start":209.424,"end":209.664,"score":0},{"word":"愧","start":209.664,"end":210.424,"score":0},{"word":"。"},{"word":"我","start":210.424,"end":210.484,"score":0.162},{"word":"們","start":210.484,"end":210.524,"score":0.145},{"word":"來","start":210.524,"end":210.664,"score":0.055},{"word":"看","start":210.664,"end":210.804,"score":0.134},{"word":"一","start":210.804,"end":210.924,"score":0.012},{"word":"下","start":210.924,"end":211.184,"score":0.065},{"word":"第","start":211.184,"end":211.324,"score":0.072},{"word":"二","start":211.324,"end":211.585,"score":0.07},{"word":"段","start":211.585,"end":212.985,"score":0.002},{"word":","},{"word":"8"},{"word":"9"},{"word":"節","start":212.985,"end":213.125,"score":0.046},{"word":"到","start":213.125,"end":213.886,"score":0.022},{"word":"9"},{"word":"6"},{"word":"節","start":213.886,"end":214.326,"score":0.021},{"word":","},{"word":"是","start":214.326,"end":214.866,"score":0},{"word":"第","start":214.866,"end":214.986,"score":0},{"word":"1"},{"word":"2"},{"word":"個","start":214.986,"end":215.706,"score":0.025},{"word":"字","start":215.706,"end":215.927,"score":0},{"word":"母","start":215.927,"end":217.247,"score":0},{"word":"L","start":217.247,"end":217.587,"score":0},{"word":"a"},{"word":"m"},{"word":"e"},{"word":"d","start":217.587,"end":217.747,"score":0},{"word":"。"},{"word":"8"},{"word":"9"},{"word":"節","start":217.747,"end":218.308,"score":0.007},{"word":","},{"word":"耶","start":218.308,"end":218.448,"score":0},{"word":"和","start":218.448,"end":218.768,"score":0.001},{"word":"華","start":218.768,"end":218.928,"score":0.006},{"word":"啊","start":218.928,"end":219.768,"score":0},{"word":","},{"word":"你","start":219.768,"end":219.888,"score":0.038},{"word":"的","start":219.888,"end":220.169,"score":0.066},{"word":"話","start":220.169,"end":220.449,"score":0.028},{"word":"安","start":220.449,"end":220.789,"score":0.032},{"word":"定","start":220.789,"end":221.009,"score":0.06},{"word":"在","start":221.009,"end":221.289,"score":0.027},{"word":"天","start":221.289,"end":221.909,"score":0},{"word":","},{"word":"直","start":221.909,"end":222.109,"score":0},{"word":"到","start":222.109,"end":222.35,"score":0.077},{"word":"永","start":222.35,"end":222.63,"score":0.007},{"word":"遠","start":222.63,"end":223.73,"score":0.002},{"word":"。"},{"word":"第","start":223.73,"end":224.19,"score":0.015},{"word":"8"},{"word":"9"},{"word":"節","start":224.19,"end":224.631,"score":0},{"word":"的","start":224.631,"end":224.831,"score":0.087},{"word":"第","start":224.831,"end":224.951,"score":0.049},{"word":"一","start":224.951,"end":225.031,"score":0.046},{"word":"個","start":225.031,"end":225.231,"score":0.053},{"word":"字","start":225.231,"end":225.431,"score":0.004},{"word":"母","start":225.431,"end":225.591,"score":0.018},{"word":"原","start":225.591,"end":225.791,"score":0.013},{"word":"文","start":225.791,"end":225.991,"score":0.007},{"word":"是","start":225.991,"end":226.231,"score":0.003},{"word":"直","start":226.231,"end":226.391,"score":0.009},{"word":"到","start":226.391,"end":226.632,"score":0.069},{"word":"永","start":226.632,"end":226.892,"score":0},{"word":"遠","start":226.892,"end":227.292,"score":0.003},{"word":","},{"word":"所","start":227.292,"end":227.392,"score":0.003},{"word":"以","start":227.392,"end":227.472,"score":0},{"word":"它","start":227.472,"end":227.652,"score":0},{"word":"也","start":227.652,"end":227.732,"score":0},{"word":"是","start":227.732,"end":228.092,"score":0.001},{"word":"接","start":228.092,"end":228.112,"score":0},{"word":"下","start":228.112,"end":228.212,"score":0.006},{"word":"來","start":228.212,"end":228.452,"score":0.082},{"word":"8"},{"word":"節","start":228.452,"end":228.652,"score":0},{"word":"的","start":228.652,"end":229.033,"score":0},{"word":"關","start":229.033,"end":229.313,"score":0.035},{"word":"鍵","start":229.313,"end":229.573,"score":0.002},{"word":"字","start":229.573,"end":229.593,"score":0.478},{"word":"。"}]},{"start":230.555,"end":251.782,"text":"耶和華的話語安定在天,直到永遠。你的誠實存到萬代,你堅定的地,地就常存。天地照你的安排存到今日,萬物都是你的仆役。在這邊詩人說,神的話語安定在天,","words":[{"word":"耶","start":230.555,"end":230.695,"score":0},{"word":"和","start":230.695,"end":230.935,"score":0},{"word":"華","start":230.935,"end":231.115,"score":0.044},{"word":"的","start":231.115,"end":231.335,"score":0.061},{"word":"話","start":231.335,"end":231.855,"score":0},{"word":"語","start":231.855,"end":232.536,"score":0.001},{"word":"安","start":232.536,"end":232.736,"score":0},{"word":"定","start":232.736,"end":232.996,"score":0.045},{"word":"在","start":232.996,"end":233.296,"score":0.001},{"word":"天","start":233.296,"end":233.816,"score":0.028},{"word":","},{"word":"直","start":233.816,"end":233.996,"score":0.029},{"word":"到","start":233.996,"end":234.216,"score":0},{"word":"永","start":234.216,"end":234.516,"score":0},{"word":"遠","start":234.516,"end":235.217,"score":0.001},{"word":"。"},{"word":"你","start":235.217,"end":235.377,"score":0.111},{"word":"的","start":235.377,"end":235.617,"score":0.075},{"word":"誠","start":235.617,"end":235.937,"score":0.005},{"word":"實","start":235.937,"end":236.057,"score":0.008},{"word":"存","start":236.057,"end":236.577,"score":0},{"word":"到","start":236.577,"end":236.777,"score":0},{"word":"萬","start":236.777,"end":237.057,"score":0.045},{"word":"代","start":237.057,"end":237.837,"score":0.011},{"word":","},{"word":"你","start":237.837,"end":238.177,"score":0.054},{"word":"堅","start":238.177,"end":238.418,"score":0.012},{"word":"定","start":238.418,"end":238.578,"score":0.091},{"word":"的","start":238.578,"end":238.818,"score":0.069},{"word":"地","start":238.818,"end":239.578,"score":0.022},{"word":","},{"word":"地","start":239.578,"end":239.858,"score":0.002},{"word":"就","start":239.858,"end":240.118,"score":0.029},{"word":"常","start":240.118,"end":240.458,"score":0},{"word":"存","start":240.458,"end":241.218,"score":0},{"word":"。"},{"word":"天","start":241.218,"end":241.619,"score":0.044},{"word":"地","start":241.619,"end":241.799,"score":0},{"word":"照","start":241.799,"end":242.479,"score":0.009},{"word":"你","start":242.479,"end":242.619,"score":0.038},{"word":"的","start":242.619,"end":242.759,"score":0.116},{"word":"安","start":242.759,"end":243.019,"score":0.061},{"word":"排","start":243.019,"end":243.499,"score":0},{"word":"存","start":243.499,"end":243.779,"score":0.018},{"word":"到","start":243.779,"end":244.059,"score":0.065},{"word":"今","start":244.059,"end":244.319,"score":0.02},{"word":"日","start":244.319,"end":245.1,"score":0.024},{"word":","},{"word":"萬","start":245.1,"end":245.32,"score":0.061},{"word":"物","start":245.32,"end":245.66,"score":0.003},{"word":"都","start":245.66,"end":245.96,"score":0.066},{"word":"是","start":245.96,"end":246.16,"score":0.015},{"word":"你","start":246.16,"end":246.3,"score":0.001},{"word":"的","start":246.3,"end":246.5,"score":0.091},{"word":"仆","start":246.5,"end":246.78,"score":0},{"word":"役","start":246.78,"end":248.321,"score":0},{"word":"。"},{"word":"在","start":248.321,"end":248.441,"score":0.128},{"word":"這","start":248.441,"end":248.601,"score":0.014},{"word":"邊","start":248.601,"end":248.801,"score":0.075},{"word":"詩","start":248.801,"end":248.921,"score":0},{"word":"人","start":248.921,"end":249.221,"score":0.012},{"word":"說","start":249.221,"end":250.061,"score":0.024},{"word":","},{"word":"神","start":250.061,"end":250.201,"score":0.003},{"word":"的","start":250.201,"end":250.421,"score":0.001},{"word":"話","start":250.421,"end":250.642,"score":0.025},{"word":"語","start":250.642,"end":250.862,"score":0},{"word":"安","start":250.862,"end":251.202,"score":0.055},{"word":"定","start":251.202,"end":251.442,"score":0},{"word":"在","start":251.442,"end":251.762,"score":0.056},{"word":"天","start":251.762,"end":251.782,"score":0.945},{"word":","}]},{"start":252.585,"end":281.443,"text":"神的話語也堅定了地。神的話語更在人類的生命裡面,誠實存到萬代。天地也都是照神的安排,才能夠到今日仍然存在。萬物也都是上帝的仆人,以至於直到如今,萬物也都照神的安排繼續來運行。這邊讓我們知道一件事情,這個看起來這些常存的天啊,","words":[{"word":"神","start":252.585,"end":252.805,"score":0.002},{"word":"的","start":252.805,"end":253.025,"score":0.063},{"word":"話","start":253.025,"end":253.205,"score":0.045},{"word":"語","start":253.205,"end":253.426,"score":0.011},{"word":"也","start":253.426,"end":253.846,"score":0.004},{"word":"堅","start":253.846,"end":254.166,"score":0},{"word":"定","start":254.166,"end":254.346,"score":0.092},{"word":"了","start":254.346,"end":254.626,"score":0},{"word":"地","start":254.626,"end":255.267,"score":0},{"word":"。"},{"word":"神","start":255.267,"end":255.427,"score":0},{"word":"的","start":255.427,"end":255.507,"score":0.001},{"word":"話","start":255.507,"end":255.887,"score":0},{"word":"語","start":255.887,"end":256.307,"score":0.005},{"word":"更","start":256.307,"end":256.888,"score":0.022},{"word":"在","start":256.888,"end":257.168,"score":0.064},{"word":"人","start":257.168,"end":257.448,"score":0.07},{"word":"類","start":257.448,"end":257.668,"score":0.066},{"word":"的","start":257.668,"end":257.928,"score":0.076},{"word":"生","start":257.928,"end":258.089,"score":0.034},{"word":"命","start":258.089,"end":258.229,"score":0.082},{"word":"裡","start":258.229,"end":258.389,"score":0},{"word":"面","start":258.389,"end":258.489,"score":0.115},{"word":","},{"word":"誠","start":258.489,"end":259.529,"score":0},{"word":"實","start":259.529,"end":259.67,"score":0.037},{"word":"存","start":259.67,"end":260.23,"score":0},{"word":"到","start":260.23,"end":260.51,"score":0.059},{"word":"萬","start":260.51,"end":260.77,"score":0.06},{"word":"代","start":260.77,"end":262.151,"score":0.008},{"word":"。"},{"word":"天","start":262.151,"end":262.411,"score":0.076},{"word":"地","start":262.411,"end":262.591,"score":0.099},{"word":"也","start":262.591,"end":262.732,"score":0.101},{"word":"都","start":262.732,"end":262.872,"score":0.142},{"word":"是","start":262.872,"end":263.072,"score":0.002},{"word":"照","start":263.072,"end":263.372,"score":0.001},{"word":"神","start":263.372,"end":263.512,"score":0.001},{"word":"的","start":263.512,"end":263.612,"score":0.005},{"word":"安","start":263.612,"end":263.852,"score":0.026},{"word":"排","start":263.852,"end":264.493,"score":0.003},{"word":","},{"word":"才","start":264.493,"end":264.593,"score":0},{"word":"能","start":264.593,"end":264.753,"score":0.021},{"word":"夠","start":264.753,"end":264.853,"score":0},{"word":"到","start":264.853,"end":265.293,"score":0},{"word":"今","start":265.293,"end":265.513,"score":0.006},{"word":"日","start":265.513,"end":265.553,"score":0.479},{"word":"仍","start":265.553,"end":266.174,"score":0},{"word":"然","start":266.174,"end":266.474,"score":0.005},{"word":"存","start":266.474,"end":266.754,"score":0.004},{"word":"在","start":266.754,"end":267.575,"score":0.021},{"word":"。"},{"word":"萬","start":267.575,"end":267.795,"score":0.074},{"word":"物","start":267.795,"end":268.015,"score":0.003},{"word":"也","start":268.015,"end":268.275,"score":0.023},{"word":"都","start":268.275,"end":268.475,"score":0},{"word":"是","start":268.475,"end":268.775,"score":0.057},{"word":"上","start":268.775,"end":269.416,"score":0.016},{"word":"帝","start":269.416,"end":269.536,"score":0},{"word":"的","start":269.536,"end":269.576,"score":0},{"word":"仆","start":269.576,"end":269.736,"score":0},{"word":"人","start":269.736,"end":270.156,"score":0.035},{"word":","},{"word":"以","start":270.156,"end":270.356,"score":0},{"word":"至","start":270.356,"end":270.476,"score":0},{"word":"於","start":270.476,"end":270.797,"score":0},{"word":"直","start":270.797,"end":270.957,"score":0.002},{"word":"到","start":270.957,"end":271.177,"score":0.07},{"word":"如","start":271.177,"end":271.417,"score":0.002},{"word":"今","start":271.417,"end":272.077,"score":0},{"word":","},{"word":"萬","start":272.077,"end":272.318,"score":0.07},{"word":"物","start":272.318,"end":272.498,"score":0.004},{"word":"也","start":272.498,"end":272.678,"score":0.014},{"word":"都","start":272.678,"end":272.898,"score":0.088},{"word":"照","start":272.898,"end":273.218,"score":0.004},{"word":"神","start":273.218,"end":273.238,"score":0.005},{"word":"的","start":273.238,"end":273.699,"score":0.001},{"word":"安","start":273.699,"end":273.959,"score":0.011},{"word":"排","start":273.959,"end":274.519,"score":0.01},{"word":"繼","start":274.519,"end":274.719,"score":0.001},{"word":"續","start":274.719,"end":274.819,"score":0.007},{"word":"來","start":274.819,"end":274.999,"score":0.086},{"word":"運","start":274.999,"end":275.34,"score":0.011},{"word":"行","start":275.34,"end":275.98,"score":0},{"word":"。"},{"word":"這","start":275.98,"end":276.08,"score":0.017},{"word":"邊","start":276.08,"end":276.22,"score":0.003},{"word":"讓","start":276.22,"end":276.34,"score":0.163},{"word":"我","start":276.34,"end":276.4,"score":0.218},{"word":"們","start":276.4,"end":276.52,"score":0.143},{"word":"知","start":276.52,"end":276.62,"score":0.079},{"word":"道","start":276.62,"end":276.781,"score":0.028},{"word":"一","start":276.781,"end":276.941,"score":0.116},{"word":"件","start":276.941,"end":277.121,"score":0.049},{"word":"事","start":277.121,"end":277.381,"score":0.034},{"word":"情","start":277.381,"end":278.241,"score":0.014},{"word":","},{"word":"這","start":278.241,"end":278.422,"score":0.094},{"word":"個","start":278.422,"end":278.762,"score":0.059},{"word":"看","start":278.762,"end":279.002,"score":0.074},{"word":"起","start":279.002,"end":279.122,"score":0.004},{"word":"來","start":279.122,"end":279.622,"score":0.039},{"word":"這","start":279.622,"end":279.842,"score":0.041},{"word":"些","start":279.842,"end":280.303,"score":0},{"word":"常","start":280.303,"end":280.603,"score":0.009},{"word":"存","start":280.603,"end":280.863,"score":0.007},{"word":"的","start":280.863,"end":281.123,"score":0.058},{"word":"天","start":281.123,"end":281.423,"score":0.06},{"word":"啊","start":281.423,"end":281.443,"score":0.334},{"word":","}]},{"start":282.637,"end":306.796,"text":"堅固的地,運轉到今日的天地萬物,其實背後都是因為神的話語托住他們。所以,一思想到天,一思想到地,一看見萬物的運作,始終是這樣的,被神的大能托住。我們就越發的相信,神的話語存到永遠。","words":[{"word":"堅","start":282.637,"end":283.037,"score":0.005},{"word":"固","start":283.037,"end":283.197,"score":0.01},{"word":"的","start":283.197,"end":283.718,"score":0.038},{"word":"地","start":283.718,"end":284.839,"score":0},{"word":","},{"word":"運","start":284.839,"end":285.139,"score":0.053},{"word":"轉","start":285.139,"end":285.379,"score":0.072},{"word":"到","start":285.379,"end":285.639,"score":0.072},{"word":"今","start":285.639,"end":285.9,"score":0.011},{"word":"日","start":285.9,"end":286.14,"score":0.015},{"word":"的","start":286.14,"end":286.76,"score":0.032},{"word":"天","start":286.76,"end":287.04,"score":0.059},{"word":"地","start":287.04,"end":287.341,"score":0.053},{"word":"萬","start":287.341,"end":287.541,"score":0.075},{"word":"物","start":287.541,"end":287.821,"score":0.032},{"word":","},{"word":"其","start":287.821,"end":288.862,"score":0},{"word":"實","start":288.862,"end":289.062,"score":0},{"word":"背","start":289.062,"end":289.282,"score":0.012},{"word":"後","start":289.282,"end":289.702,"score":0.021},{"word":"都","start":289.702,"end":289.863,"score":0.106},{"word":"是","start":289.863,"end":290.043,"score":0.109},{"word":"因","start":290.043,"end":290.083,"score":0},{"word":"為","start":290.083,"end":290.303,"score":0.006},{"word":"神","start":290.303,"end":290.483,"score":0.003},{"word":"的","start":290.483,"end":290.503,"score":0.002},{"word":"話","start":290.503,"end":290.883,"score":0},{"word":"語","start":290.883,"end":291.084,"score":0.001},{"word":"托","start":291.084,"end":291.364,"score":0.004},{"word":"住","start":291.364,"end":291.584,"score":0.007},{"word":"他","start":291.584,"end":291.764,"score":0.002},{"word":"們","start":291.764,"end":292.545,"score":0},{"word":"。"},{"word":"所","start":292.545,"end":292.705,"score":0.01},{"word":"以","start":292.705,"end":293.385,"score":0.019},{"word":","},{"word":"一","start":293.385,"end":293.525,"score":0},{"word":"思","start":293.525,"end":293.686,"score":0},{"word":"想","start":293.686,"end":293.886,"score":0.072},{"word":"到","start":293.886,"end":294.186,"score":0.063},{"word":"天","start":294.186,"end":294.886,"score":0.026},{"word":","},{"word":"一","start":294.886,"end":295.047,"score":0.118},{"word":"思","start":295.047,"end":295.207,"score":0.009},{"word":"想","start":295.207,"end":295.427,"score":0.058},{"word":"到","start":295.427,"end":295.727,"score":0},{"word":"地","start":295.727,"end":296.268,"score":0.028},{"word":","},{"word":"一","start":296.268,"end":296.408,"score":0.082},{"word":"看","start":296.408,"end":296.628,"score":0.001},{"word":"見","start":296.628,"end":296.908,"score":0.005},{"word":"萬","start":296.908,"end":297.048,"score":0.104},{"word":"物","start":297.048,"end":297.208,"score":0.045},{"word":"的","start":297.208,"end":297.388,"score":0.105},{"word":"運","start":297.388,"end":297.729,"score":0.042},{"word":"作","start":297.729,"end":298.709,"score":0.013},{"word":","},{"word":"始","start":298.709,"end":298.89,"score":0.008},{"word":"終","start":298.89,"end":299.11,"score":0.004},{"word":"是","start":299.11,"end":299.21,"score":0.008},{"word":"這","start":299.21,"end":299.27,"score":0.091},{"word":"樣","start":299.27,"end":299.53,"score":0.022},{"word":"的","start":299.53,"end":300.311,"score":0.025},{"word":","},{"word":"被","start":300.311,"end":300.371,"score":0.194},{"word":"神","start":300.371,"end":301.091,"score":0},{"word":"的","start":301.091,"end":301.251,"score":0.036},{"word":"大","start":301.251,"end":301.412,"score":0.06},{"word":"能","start":301.412,"end":301.532,"score":0.14},{"word":"托","start":301.532,"end":301.992,"score":0},{"word":"住","start":301.992,"end":302.652,"score":0.005},{"word":"。"},{"word":"我","start":302.652,"end":302.753,"score":0.198},{"word":"們","start":302.753,"end":302.913,"score":0.124},{"word":"就","start":302.913,"end":303.193,"score":0.06},{"word":"越","start":303.193,"end":303.333,"score":0},{"word":"發","start":303.333,"end":303.473,"score":0.003},{"word":"的","start":303.473,"end":303.673,"score":0.058},{"word":"相","start":303.673,"end":303.893,"score":0.001},{"word":"信","start":303.893,"end":304.694,"score":0.001},{"word":","},{"word":"神","start":304.694,"end":304.834,"score":0.002},{"word":"的","start":304.834,"end":305.114,"score":0.001},{"word":"話","start":305.114,"end":305.275,"score":0.031},{"word":"語","start":305.275,"end":305.975,"score":0.004},{"word":"存","start":305.975,"end":306.215,"score":0},{"word":"到","start":306.215,"end":306.475,"score":0},{"word":"永","start":306.475,"end":306.776,"score":0.022},{"word":"遠","start":306.776,"end":306.796,"score":0.111},{"word":"。"}]},{"start":307.841,"end":333.859,"text":"九十二節我若不是喜愛你的律法早就在苦難中滅絕了我永不忘記你的訊詞因你用這訊詞將我救活了我是屬你的求你救我因我尋求了你的訊詞惡人等待我要滅絕我我卻要揣摩你的法度我看萬事盡都有限","words":[{"word":"九","start":307.841,"end":308.101,"score":0.036},{"word":"十","start":308.101,"end":308.221,"score":0.003},{"word":"二","start":308.221,"end":308.481,"score":0.054},{"word":"節","start":308.481,"end":308.762,"score":0.006},{"word":"我","start":308.762,"end":309.022,"score":0.027},{"word":"若","start":309.022,"end":309.162,"score":0.11},{"word":"不","start":309.162,"end":309.342,"score":0.111},{"word":"是","start":309.342,"end":309.622,"score":0.049},{"word":"喜","start":309.622,"end":309.782,"score":0.022},{"word":"愛","start":309.782,"end":309.962,"score":0.011},{"word":"你","start":309.962,"end":310.063,"score":0.177},{"word":"的","start":310.063,"end":310.243,"score":0.057},{"word":"律","start":310.243,"end":310.543,"score":0.005},{"word":"法","start":310.543,"end":311.203,"score":0.022},{"word":"早","start":311.203,"end":311.604,"score":0.011},{"word":"就","start":311.604,"end":311.764,"score":0.107},{"word":"在","start":311.764,"end":312.064,"score":0.062},{"word":"苦","start":312.064,"end":312.244,"score":0.001},{"word":"難","start":312.244,"end":312.484,"score":0.011},{"word":"中","start":312.484,"end":312.764,"score":0.001},{"word":"滅","start":312.764,"end":313.165,"score":0.001},{"word":"絕","start":313.165,"end":313.265,"score":0},{"word":"了","start":313.265,"end":314.145,"score":0.019},{"word":"我","start":314.145,"end":314.305,"score":0},{"word":"永","start":314.305,"end":314.526,"score":0.011},{"word":"不","start":314.526,"end":314.726,"score":0.099},{"word":"忘","start":314.726,"end":315.006,"score":0.032},{"word":"記","start":315.006,"end":315.166,"score":0.001},{"word":"你","start":315.166,"end":315.246,"score":0},{"word":"的","start":315.246,"end":315.506,"score":0.076},{"word":"訊","start":315.506,"end":315.786,"score":0},{"word":"詞","start":315.786,"end":316.647,"score":0},{"word":"因","start":316.647,"end":316.827,"score":0.026},{"word":"你","start":316.827,"end":317.067,"score":0.076},{"word":"用","start":317.067,"end":317.388,"score":0.06},{"word":"這","start":317.388,"end":317.688,"score":0.064},{"word":"訊","start":317.688,"end":318.088,"score":0.035},{"word":"詞","start":318.088,"end":318.749,"score":0},{"word":"將","start":318.749,"end":319.129,"score":0},{"word":"我","start":319.129,"end":319.669,"score":0.036},{"word":"救","start":319.669,"end":320.029,"score":0},{"word":"活","start":320.029,"end":320.149,"score":0},{"word":"了","start":320.149,"end":320.169,"score":0.885},{"word":"我","start":320.169,"end":321.05,"score":0},{"word":"是","start":321.05,"end":321.31,"score":0.073},{"word":"屬","start":321.31,"end":321.53,"score":0.006},{"word":"你","start":321.53,"end":321.65,"score":0.044},{"word":"的","start":321.65,"end":322.251,"score":0.033},{"word":"求","start":322.251,"end":322.391,"score":0.106},{"word":"你","start":322.391,"end":322.611,"score":0.005},{"word":"救","start":322.611,"end":322.931,"score":0},{"word":"我","start":322.931,"end":323.292,"score":0.038},{"word":"因","start":323.292,"end":323.892,"score":0},{"word":"我","start":323.892,"end":324.072,"score":0.097},{"word":"尋","start":324.072,"end":324.352,"score":0.005},{"word":"求","start":324.352,"end":324.512,"score":0.096},{"word":"了","start":324.512,"end":324.653,"score":0.022},{"word":"你","start":324.653,"end":324.713,"score":0.285},{"word":"的","start":324.713,"end":325.013,"score":0},{"word":"訊","start":325.013,"end":325.313,"score":0},{"word":"詞","start":325.313,"end":326.954,"score":0.003},{"word":"惡","start":326.954,"end":327.114,"score":0.011},{"word":"人","start":327.114,"end":327.334,"score":0.065},{"word":"等","start":327.334,"end":327.535,"score":0.047},{"word":"待","start":327.535,"end":327.695,"score":0.007},{"word":"我","start":327.695,"end":328.295,"score":0},{"word":"要","start":328.295,"end":328.515,"score":0},{"word":"滅","start":328.515,"end":328.775,"score":0.002},{"word":"絕","start":328.775,"end":329.516,"score":0},{"word":"我","start":329.516,"end":329.576,"score":0.002},{"word":"我","start":329.576,"end":329.736,"score":0.12},{"word":"卻","start":329.736,"end":329.916,"score":0.007},{"word":"要","start":329.916,"end":330.216,"score":0.061},{"word":"揣","start":330.216,"end":330.557,"score":0},{"word":"摩","start":330.557,"end":330.817,"score":0.001},{"word":"你","start":330.817,"end":330.977,"score":0.109},{"word":"的","start":330.977,"end":331.157,"score":0.101},{"word":"法","start":331.157,"end":331.377,"score":0},{"word":"度","start":331.377,"end":332.078,"score":0.007},{"word":"我","start":332.078,"end":332.198,"score":0},{"word":"看","start":332.198,"end":332.478,"score":0.038},{"word":"萬","start":332.478,"end":332.778,"score":0.046},{"word":"事","start":332.778,"end":333.078,"score":0.002},{"word":"盡","start":333.078,"end":333.339,"score":0.001},{"word":"都","start":333.339,"end":333.559,"score":0.09},{"word":"有","start":333.559,"end":333.839,"score":0.069},{"word":"限","start":333.839,"end":333.859,"score":0.156}]},{"start":334.377,"end":355.32,"text":"唯有祢的命令極其寬廣。神的話語存到永遠。而在世界上我們要面對很多的這些挑戰。包含苦難、包含仇敵的詭計、包含罪的試探跟誘惑。","words":[{"word":"唯","start":334.377,"end":334.697,"score":0.011},{"word":"有","start":334.697,"end":335.158,"score":0.033},{"word":"祢"},{"word":"的","start":335.158,"end":335.618,"score":0.043},{"word":"命","start":335.618,"end":335.879,"score":0},{"word":"令","start":335.879,"end":336.239,"score":0.018},{"word":"極","start":336.239,"end":336.64,"score":0},{"word":"其","start":336.64,"end":337.16,"score":0.005},{"word":"寬","start":337.16,"end":337.52,"score":0},{"word":"廣","start":337.52,"end":338.381,"score":0.001},{"word":"。"},{"word":"神","start":338.381,"end":338.602,"score":0.008},{"word":"的","start":338.602,"end":338.922,"score":0.046},{"word":"話","start":338.922,"end":339.202,"score":0},{"word":"語","start":339.202,"end":339.743,"score":0},{"word":"存","start":339.743,"end":340.023,"score":0.022},{"word":"到","start":340.023,"end":340.344,"score":0},{"word":"永","start":340.344,"end":340.664,"score":0.002},{"word":"遠","start":340.664,"end":341.585,"score":0.007},{"word":"。"},{"word":"而","start":341.585,"end":342.506,"score":0.011},{"word":"在","start":342.506,"end":342.806,"score":0.051},{"word":"世","start":342.806,"end":342.987,"score":0.003},{"word":"界","start":342.987,"end":343.187,"score":0.09},{"word":"上","start":343.187,"end":343.447,"score":0.047},{"word":"我","start":343.447,"end":343.607,"score":0.032},{"word":"們","start":343.607,"end":343.767,"score":0.062},{"word":"要","start":343.767,"end":344.408,"score":0.03},{"word":"面","start":344.408,"end":344.668,"score":0.027},{"word":"對","start":344.668,"end":345.67,"score":0.018},{"word":"很","start":345.67,"end":345.91,"score":0.003},{"word":"多","start":345.91,"end":346.09,"score":0.109},{"word":"的","start":346.09,"end":346.31,"score":0},{"word":"這","start":346.31,"end":346.47,"score":0.005},{"word":"些","start":346.47,"end":346.691,"score":0},{"word":"挑","start":346.691,"end":346.971,"score":0.006},{"word":"戰","start":346.971,"end":347.652,"score":0},{"word":"。"},{"word":"包","start":347.652,"end":347.792,"score":0},{"word":"含","start":347.792,"end":348.132,"score":0},{"word":"苦","start":348.132,"end":348.473,"score":0.001},{"word":"難","start":348.473,"end":349.234,"score":0.001},{"word":"、"},{"word":"包","start":349.234,"end":349.454,"score":0.084},{"word":"含","start":349.454,"end":349.974,"score":0.012},{"word":"仇","start":349.974,"end":350.755,"score":0},{"word":"敵","start":350.755,"end":350.995,"score":0},{"word":"的","start":350.995,"end":351.396,"score":0.008},{"word":"詭","start":351.396,"end":351.676,"score":0},{"word":"計","start":351.676,"end":352.377,"score":0.003},{"word":"、"},{"word":"包","start":352.377,"end":352.657,"score":0.001},{"word":"含","start":352.657,"end":353.478,"score":0.006},{"word":"罪","start":353.478,"end":353.739,"score":0},{"word":"的","start":353.739,"end":354.039,"score":0.066},{"word":"試","start":354.039,"end":354.259,"score":0.001},{"word":"探","start":354.259,"end":354.539,"score":0.002},{"word":"跟","start":354.539,"end":354.94,"score":0.003},{"word":"誘","start":354.94,"end":355.3,"score":0},{"word":"惑","start":355.3,"end":355.32,"score":0.137},{"word":"。"}]},{"start":355.981,"end":380.85,"text":"這些看起來都很有威力。仇敵的攻擊很有威力。魔鬼的試探也很有威力。甚至是罪惡的對我們生命中的控制也是很有威力。可是呢這一些事情呢面對比起上帝永遠常存的話語來講","words":[{"word":"這","start":355.981,"end":356.521,"score":0},{"word":"些","start":356.521,"end":357.341,"score":0.021},{"word":"看","start":357.341,"end":357.542,"score":0.09},{"word":"起","start":357.542,"end":357.622,"score":0.001},{"word":"來","start":357.622,"end":357.742,"score":0.001},{"word":"都","start":357.742,"end":357.862,"score":0.041},{"word":"很","start":357.862,"end":357.982,"score":0.14},{"word":"有","start":357.982,"end":358.562,"score":0.002},{"word":"威","start":358.562,"end":359.322,"score":0},{"word":"力","start":359.322,"end":359.462,"score":0},{"word":"。"},{"word":"仇","start":359.462,"end":359.682,"score":0},{"word":"敵","start":359.682,"end":359.862,"score":0},{"word":"的","start":359.862,"end":360.283,"score":0},{"word":"攻","start":360.283,"end":360.683,"score":0},{"word":"擊","start":360.683,"end":361.243,"score":0},{"word":"很","start":361.243,"end":361.383,"score":0.003},{"word":"有","start":361.383,"end":361.603,"score":0.01},{"word":"威","start":361.603,"end":361.843,"score":0},{"word":"力","start":361.843,"end":362.883,"score":0.003},{"word":"。"},{"word":"魔","start":362.883,"end":363.144,"score":0.008},{"word":"鬼","start":363.144,"end":363.264,"score":0.005},{"word":"的","start":363.264,"end":363.824,"score":0},{"word":"試","start":363.824,"end":364.024,"score":0.001},{"word":"探","start":364.024,"end":364.584,"score":0},{"word":"也","start":364.584,"end":364.884,"score":0.025},{"word":"很","start":364.884,"end":365.064,"score":0.002},{"word":"有","start":365.064,"end":365.624,"score":0},{"word":"威","start":365.624,"end":365.764,"score":0},{"word":"力","start":365.764,"end":366.665,"score":0},{"word":"。"},{"word":"甚","start":366.665,"end":366.925,"score":0.029},{"word":"至","start":366.925,"end":367.085,"score":0},{"word":"是","start":367.085,"end":367.405,"score":0},{"word":"罪","start":367.405,"end":367.605,"score":0},{"word":"惡","start":367.605,"end":367.845,"score":0.008},{"word":"的","start":367.845,"end":368.565,"score":0.028},{"word":"對","start":368.565,"end":368.645,"score":0.01},{"word":"我","start":368.645,"end":368.745,"score":0},{"word":"們","start":368.745,"end":368.886,"score":0},{"word":"生","start":368.886,"end":369.026,"score":0.002},{"word":"命","start":369.026,"end":369.206,"score":0.006},{"word":"中","start":369.206,"end":369.446,"score":0.012},{"word":"的","start":369.446,"end":369.906,"score":0.043},{"word":"控","start":369.906,"end":370.266,"score":0},{"word":"制","start":370.266,"end":370.886,"score":0.002},{"word":"也","start":370.886,"end":371.126,"score":0.082},{"word":"是","start":371.126,"end":371.446,"score":0},{"word":"很","start":371.446,"end":371.707,"score":0.067},{"word":"有","start":371.707,"end":372.087,"score":0},{"word":"威","start":372.087,"end":372.407,"score":0},{"word":"力","start":372.407,"end":373.067,"score":0.013},{"word":"。"},{"word":"可","start":373.067,"end":373.207,"score":0.135},{"word":"是","start":373.207,"end":373.367,"score":0.106},{"word":"呢","start":373.367,"end":373.947,"score":0},{"word":"這","start":373.947,"end":374.107,"score":0.031},{"word":"一","start":374.107,"end":374.387,"score":0.064},{"word":"些","start":374.387,"end":374.588,"score":0.078},{"word":"事","start":374.588,"end":374.848,"score":0.012},{"word":"情","start":374.848,"end":375.088,"score":0.071},{"word":"呢","start":375.088,"end":376.248,"score":0.001},{"word":"面","start":376.248,"end":376.528,"score":0.067},{"word":"對","start":376.528,"end":377.248,"score":0.026},{"word":"比","start":377.248,"end":377.529,"score":0.017},{"word":"起","start":377.529,"end":377.929,"score":0.03},{"word":"上","start":377.929,"end":378.169,"score":0},{"word":"帝","start":378.169,"end":379.109,"score":0},{"word":"永","start":379.109,"end":379.309,"score":0.066},{"word":"遠","start":379.309,"end":379.629,"score":0.021},{"word":"常","start":379.629,"end":379.889,"score":0.009},{"word":"存","start":379.889,"end":380.029,"score":0.039},{"word":"的","start":380.029,"end":380.31,"score":0.025},{"word":"話","start":380.31,"end":380.47,"score":0.012},{"word":"語","start":380.47,"end":380.55,"score":0.011},{"word":"來","start":380.55,"end":380.83,"score":0.067},{"word":"講","start":380.83,"end":380.85,"score":0.104}]},{"start":381.698,"end":410.505,"text":"苦難、試探、軟弱,都是有限的。唯有神的話語是更有能力,唯有神的話語是更寬廣,使人可以被救活。在這邊詩篇總共出現了16個這個字,在中文被翻譯成救活或存活。因此呢,只有神的話語可以使我們活過來了。","words":[{"word":"苦","start":381.698,"end":382.058,"score":0.002},{"word":"難","start":382.058,"end":383.318,"score":0.002},{"word":"、"},{"word":"試","start":383.318,"end":383.558,"score":0.001},{"word":"探","start":383.558,"end":384.599,"score":0.001},{"word":"、"},{"word":"軟","start":384.599,"end":384.959,"score":0.006},{"word":"弱","start":384.959,"end":385.899,"score":0},{"word":","},{"word":"都","start":385.899,"end":386.199,"score":0.063},{"word":"是","start":386.199,"end":386.779,"score":0.024},{"word":"有","start":386.779,"end":387.139,"score":0.054},{"word":"限","start":387.139,"end":387.459,"score":0.001},{"word":"的","start":387.459,"end":388.16,"score":0.006},{"word":"。"},{"word":"唯","start":388.16,"end":388.32,"score":0.001},{"word":"有","start":388.32,"end":388.56,"score":0.082},{"word":"神","start":388.56,"end":388.76,"score":0.001},{"word":"的","start":388.76,"end":389,"score":0},{"word":"話","start":389,"end":389.22,"score":0},{"word":"語","start":389.22,"end":389.66,"score":0},{"word":"是","start":389.66,"end":389.94,"score":0.004},{"word":"更","start":389.94,"end":390.14,"score":0.073},{"word":"有","start":390.14,"end":390.36,"score":0.084},{"word":"能","start":390.36,"end":390.58,"score":0.086},{"word":"力","start":390.58,"end":391.1,"score":0.006},{"word":","},{"word":"唯","start":391.1,"end":391.18,"score":0},{"word":"有","start":391.18,"end":391.24,"score":0.236},{"word":"神","start":391.24,"end":391.54,"score":0},{"word":"的","start":391.54,"end":391.74,"score":0},{"word":"話","start":391.74,"end":391.92,"score":0},{"word":"語","start":391.92,"end":392.501,"score":0.009},{"word":"是","start":392.501,"end":392.841,"score":0.053},{"word":"更","start":392.841,"end":393.621,"score":0.019},{"word":"寬","start":393.621,"end":393.901,"score":0},{"word":"廣","start":393.901,"end":394.361,"score":0},{"word":","},{"word":"使","start":394.361,"end":394.561,"score":0.001},{"word":"人","start":394.561,"end":394.981,"score":0.04},{"word":"可","start":394.981,"end":395.141,"score":0.124},{"word":"以","start":395.141,"end":395.821,"score":0.028},{"word":"被","start":395.821,"end":396.061,"score":0.066},{"word":"救","start":396.061,"end":396.602,"score":0},{"word":"活","start":396.602,"end":398.182,"score":0.003},{"word":"。"},{"word":"在","start":398.182,"end":398.322,"score":0.132},{"word":"這","start":398.322,"end":398.502,"score":0.108},{"word":"邊","start":398.502,"end":398.962,"score":0.04},{"word":"詩","start":398.962,"end":399.222,"score":0},{"word":"篇","start":399.222,"end":400.743,"score":0.003},{"word":"總","start":400.743,"end":400.943,"score":0.016},{"word":"共","start":400.943,"end":401.203,"score":0.024},{"word":"出","start":401.203,"end":401.403,"score":0.046},{"word":"現","start":401.403,"end":401.943,"score":0.007},{"word":"了","start":401.943,"end":402.123,"score":0},{"word":"1"},{"word":"6"},{"word":"個","start":402.123,"end":402.283,"score":0.102},{"word":"這","start":402.283,"end":402.363,"score":0},{"word":"個","start":402.363,"end":402.503,"score":0.026},{"word":"字","start":402.503,"end":403.063,"score":0.004},{"word":","},{"word":"在","start":403.063,"end":403.263,"score":0.001},{"word":"中","start":403.263,"end":403.403,"score":0},{"word":"文","start":403.403,"end":403.583,"score":0.068},{"word":"被","start":403.583,"end":403.783,"score":0.044},{"word":"翻","start":403.783,"end":403.903,"score":0.016},{"word":"譯","start":403.903,"end":404.083,"score":0},{"word":"成","start":404.083,"end":404.463,"score":0.012},{"word":"救","start":404.463,"end":404.664,"score":0.015},{"word":"活","start":404.664,"end":405.424,"score":0},{"word":"或","start":405.424,"end":405.584,"score":0.003},{"word":"存","start":405.584,"end":406.104,"score":0},{"word":"活","start":406.104,"end":407.004,"score":0.001},{"word":"。"},{"word":"因","start":407.004,"end":407.224,"score":0.022},{"word":"此","start":407.224,"end":407.404,"score":0.001},{"word":"呢","start":407.404,"end":407.764,"score":0},{"word":","},{"word":"只","start":407.764,"end":407.924,"score":0},{"word":"有","start":407.924,"end":408.184,"score":0},{"word":"神","start":408.184,"end":408.204,"score":0},{"word":"的","start":408.204,"end":408.424,"score":0},{"word":"話","start":408.424,"end":408.564,"score":0},{"word":"語","start":408.564,"end":409.205,"score":0},{"word":"可","start":409.205,"end":409.365,"score":0.124},{"word":"以","start":409.365,"end":409.545,"score":0.109},{"word":"使","start":409.545,"end":409.645,"score":0},{"word":"我","start":409.645,"end":409.805,"score":0.001},{"word":"們","start":409.805,"end":410.085,"score":0},{"word":"活","start":410.085,"end":410.205,"score":0},{"word":"過","start":410.205,"end":410.365,"score":0.081},{"word":"來","start":410.365,"end":410.485,"score":0.165},{"word":"了","start":410.485,"end":410.505,"score":0},{"word":"。"}]},{"start":411.323,"end":436.692,"text":"因此呢,八十九節到九十六節,給我們一個很寶貴的應許,要信靠神的話語。因為祂的話語,比天、比地、比你看見的萬物,都還要存到永遠。能力勝過我們所面對的苦難、軟弱、誘惑、試探,甚至我們的失敗。","words":[{"word":"因","start":411.323,"end":411.523,"score":0.006},{"word":"此","start":411.523,"end":411.663,"score":0.054},{"word":"呢","start":411.663,"end":411.823,"score":0},{"word":","},{"word":"八","start":411.823,"end":411.943,"score":0.082},{"word":"十","start":411.943,"end":412.123,"score":0.003},{"word":"九","start":412.123,"end":412.363,"score":0.027},{"word":"節","start":412.363,"end":412.603,"score":0.015},{"word":"到","start":412.603,"end":412.884,"score":0.058},{"word":"九","start":412.884,"end":414.304,"score":0.004},{"word":"十","start":414.304,"end":414.444,"score":0.001},{"word":"六","start":414.444,"end":414.764,"score":0.054},{"word":"節","start":414.764,"end":414.944,"score":0.02},{"word":","},{"word":"給","start":414.944,"end":415.044,"score":0},{"word":"我","start":415.044,"end":415.064,"score":0},{"word":"們","start":415.064,"end":415.104,"score":0.001},{"word":"一","start":415.104,"end":415.184,"score":0.003},{"word":"個","start":415.184,"end":415.304,"score":0.156},{"word":"很","start":415.304,"end":415.564,"score":0.019},{"word":"寶","start":415.564,"end":415.785,"score":0},{"word":"貴","start":415.785,"end":415.905,"score":0},{"word":"的","start":415.905,"end":416.085,"score":0.106},{"word":"應","start":416.085,"end":416.465,"score":0.024},{"word":"許","start":416.465,"end":417.505,"score":0.013},{"word":","},{"word":"要","start":417.505,"end":417.785,"score":0.071},{"word":"信","start":417.785,"end":417.965,"score":0.017},{"word":"靠","start":417.965,"end":418.225,"score":0},{"word":"神","start":418.225,"end":418.345,"score":0},{"word":"的","start":418.345,"end":418.586,"score":0.002},{"word":"話","start":418.586,"end":418.766,"score":0.021},{"word":"語","start":418.766,"end":419.306,"score":0.004},{"word":"。"},{"word":"因","start":419.306,"end":419.446,"score":0.067},{"word":"為","start":419.446,"end":419.466,"score":0.891},{"word":"祂"},{"word":"的","start":419.466,"end":419.526,"score":0},{"word":"話","start":419.526,"end":420.046,"score":0},{"word":"語","start":420.046,"end":420.846,"score":0},{"word":","},{"word":"比","start":420.846,"end":421.086,"score":0.03},{"word":"天","start":421.086,"end":421.867,"score":0.023},{"word":"、"},{"word":"比","start":421.867,"end":422.087,"score":0},{"word":"地","start":422.087,"end":422.987,"score":0.011},{"word":"、"},{"word":"比","start":422.987,"end":423.107,"score":0.002},{"word":"你","start":423.107,"end":423.247,"score":0.029},{"word":"看","start":423.247,"end":423.567,"score":0.058},{"word":"見","start":423.567,"end":423.647,"score":0},{"word":"的","start":423.647,"end":423.867,"score":0.001},{"word":"萬","start":423.867,"end":424.027,"score":0.069},{"word":"物","start":424.027,"end":424.828,"score":0.001},{"word":","},{"word":"都","start":424.828,"end":425.008,"score":0.11},{"word":"還","start":425.008,"end":425.168,"score":0.075},{"word":"要","start":425.168,"end":425.468,"score":0.031},{"word":"存","start":425.468,"end":425.688,"score":0.024},{"word":"到","start":425.688,"end":425.928,"score":0},{"word":"永","start":425.928,"end":426.208,"score":0},{"word":"遠","start":426.208,"end":427.409,"score":0.001},{"word":"。"},{"word":"能","start":427.409,"end":427.689,"score":0.07},{"word":"力","start":427.689,"end":428.569,"score":0.001},{"word":"勝","start":428.569,"end":428.929,"score":0},{"word":"過","start":428.929,"end":429.729,"score":0.014},{"word":"我","start":429.729,"end":429.809,"score":0.249},{"word":"們","start":429.809,"end":430.109,"score":0.066},{"word":"所","start":430.109,"end":430.59,"score":0},{"word":"面","start":430.59,"end":430.81,"score":0.082},{"word":"對","start":430.81,"end":430.99,"score":0.107},{"word":"的","start":430.99,"end":431.29,"score":0.061},{"word":"苦","start":431.29,"end":431.51,"score":0},{"word":"難","start":431.51,"end":431.55,"score":0.009},{"word":"、"},{"word":"軟","start":431.55,"end":432.53,"score":0},{"word":"弱","start":432.53,"end":432.69,"score":0},{"word":"、"},{"word":"誘","start":432.69,"end":433.631,"score":0},{"word":"惑","start":433.631,"end":434.751,"score":0},{"word":"、"},{"word":"試","start":434.751,"end":434.931,"score":0},{"word":"探","start":434.931,"end":435.671,"score":0.003},{"word":","},{"word":"甚","start":435.671,"end":435.891,"score":0.023},{"word":"至","start":435.891,"end":435.992,"score":0.029},{"word":"我","start":435.992,"end":436.132,"score":0.006},{"word":"們","start":436.132,"end":436.212,"score":0.006},{"word":"的","start":436.212,"end":436.412,"score":0.1},{"word":"失","start":436.412,"end":436.672,"score":0.001},{"word":"敗","start":436.672,"end":436.692,"score":0.153},{"word":"。"}]},{"start":437.824,"end":462.847,"text":"這些誘惑軟弱失敗、苦難再怎麼大都大不過神的話。這樣的苦難跟軟弱試探持續再怎麼久都長久不過神話語永遠信實。因此我們對神要大有盼望。我們一起來禱告。主啊!我要拼死命的緊緊抓住祢的話語。","words":[{"word":"這","start":437.824,"end":438.184,"score":0.011},{"word":"些","start":438.184,"end":438.605,"score":0.046},{"word":"誘","start":438.605,"end":438.765,"score":0},{"word":"惑","start":438.765,"end":439.025,"score":0.001},{"word":"軟","start":439.025,"end":439.205,"score":0.001},{"word":"弱","start":439.205,"end":439.485,"score":0.001},{"word":"失","start":439.485,"end":439.686,"score":0},{"word":"敗","start":439.686,"end":440.326,"score":0},{"word":"、"},{"word":"苦","start":440.326,"end":440.566,"score":0.007},{"word":"難","start":440.566,"end":441.067,"score":0.004},{"word":"再","start":441.067,"end":441.247,"score":0.03},{"word":"怎","start":441.247,"end":441.367,"score":0.163},{"word":"麼","start":441.367,"end":441.707,"score":0.023},{"word":"大","start":441.707,"end":442.348,"score":0},{"word":"都","start":442.348,"end":442.748,"score":0.049},{"word":"大","start":442.748,"end":442.849,"score":0},{"word":"不","start":442.849,"end":443.089,"score":0.081},{"word":"過","start":443.089,"end":443.749,"score":0.023},{"word":"神","start":443.749,"end":443.889,"score":0.002},{"word":"的","start":443.889,"end":444.23,"score":0},{"word":"話","start":444.23,"end":444.95,"score":0},{"word":"。"},{"word":"這","start":444.95,"end":445.131,"score":0.049},{"word":"樣","start":445.131,"end":445.251,"score":0.08},{"word":"的","start":445.251,"end":445.471,"score":0.072},{"word":"苦","start":445.471,"end":445.671,"score":0},{"word":"難","start":445.671,"end":446.232,"score":0},{"word":"跟","start":446.232,"end":446.452,"score":0.059},{"word":"軟","start":446.452,"end":446.732,"score":0.009},{"word":"弱","start":446.732,"end":446.992,"score":0.002},{"word":"試","start":446.992,"end":447.112,"score":0},{"word":"探","start":447.112,"end":448.013,"score":0},{"word":"持","start":448.013,"end":448.253,"score":0.046},{"word":"續","start":448.253,"end":448.454,"score":0.069},{"word":"再","start":448.454,"end":448.734,"score":0.025},{"word":"怎","start":448.734,"end":448.854,"score":0.164},{"word":"麼","start":448.854,"end":449.134,"score":0.071},{"word":"久","start":449.134,"end":449.895,"score":0.014},{"word":"都","start":449.895,"end":450.115,"score":0},{"word":"長","start":450.115,"end":450.415,"score":0},{"word":"久","start":450.415,"end":450.595,"score":0.014},{"word":"不","start":450.595,"end":450.796,"score":0},{"word":"過","start":450.796,"end":451.496,"score":0},{"word":"神","start":451.496,"end":451.877,"score":0.002},{"word":"話","start":451.877,"end":452.077,"score":0},{"word":"語","start":452.077,"end":452.277,"score":0.018},{"word":"永","start":452.277,"end":452.517,"score":0.031},{"word":"遠","start":452.517,"end":452.797,"score":0.02},{"word":"信","start":452.797,"end":453.138,"score":0.01},{"word":"實","start":453.138,"end":453.818,"score":0.001},{"word":"。"},{"word":"因","start":453.818,"end":453.999,"score":0.008},{"word":"此","start":453.999,"end":454.099,"score":0},{"word":"我","start":454.099,"end":454.259,"score":0},{"word":"們","start":454.259,"end":454.379,"score":0},{"word":"對","start":454.379,"end":454.619,"score":0},{"word":"神","start":454.619,"end":455.2,"score":0.002},{"word":"要","start":455.2,"end":455.46,"score":0.042},{"word":"大","start":455.46,"end":455.68,"score":0.081},{"word":"有","start":455.68,"end":455.86,"score":0.015},{"word":"盼","start":455.86,"end":456.16,"score":0},{"word":"望","start":456.16,"end":456.821,"score":0},{"word":"。"},{"word":"我","start":456.821,"end":456.921,"score":0.198},{"word":"們","start":456.921,"end":457.221,"score":0.066},{"word":"一","start":457.221,"end":457.382,"score":0.123},{"word":"起","start":457.382,"end":457.482,"score":0.001},{"word":"來","start":457.482,"end":457.682,"score":0.002},{"word":"禱","start":457.682,"end":458.943,"score":0},{"word":"告","start":458.943,"end":459.323,"score":0},{"word":"。"},{"word":"主","start":459.323,"end":459.504,"score":0.004},{"word":"啊","start":459.504,"end":459.684,"score":0.009},{"word":"!"},{"word":"我","start":459.684,"end":459.784,"score":0.181},{"word":"要","start":459.784,"end":460.064,"score":0.071},{"word":"拼","start":460.064,"end":460.344,"score":0.001},{"word":"死","start":460.344,"end":460.524,"score":0.074},{"word":"命","start":460.524,"end":460.705,"score":0.003},{"word":"的","start":460.705,"end":461.245,"score":0.037},{"word":"緊","start":461.245,"end":461.445,"score":0.001},{"word":"緊","start":461.445,"end":461.786,"score":0.001},{"word":"抓","start":461.786,"end":462.166,"score":0},{"word":"住","start":462.166,"end":462.306,"score":0},{"word":"祢"},{"word":"的","start":462.306,"end":462.586,"score":0.064},{"word":"話","start":462.586,"end":462.826,"score":0.043},{"word":"語","start":462.826,"end":462.847,"score":0.241},{"word":"。"}]},{"start":463.507,"end":491.738,"text":"面對仇敵的試探。罪的誘惑。仇敵的攻擊。世界對我們的這種影響。主啊祂們要把我們拉到另外一個方向去。主啊有時候祂們的威力好大啊。大到我們不能承受。但是主我們要拼死命的抓住祢的話語。因為祢的話語。主啊大有能力。祢的話語是信實的。","words":[{"word":"面","start":463.507,"end":463.827,"score":0.046},{"word":"對","start":463.827,"end":464.828,"score":0.019},{"word":"仇","start":464.828,"end":465.548,"score":0},{"word":"敵","start":465.548,"end":465.608,"score":0},{"word":"的","start":465.608,"end":465.628,"score":0},{"word":"試","start":465.628,"end":466.008,"score":0},{"word":"探","start":466.008,"end":466.848,"score":0.001},{"word":"。"},{"word":"罪","start":466.848,"end":467.128,"score":0},{"word":"的","start":467.128,"end":467.449,"score":0.062},{"word":"誘","start":467.449,"end":467.849,"score":0},{"word":"惑","start":467.849,"end":468.689,"score":0},{"word":"。"},{"word":"仇","start":468.689,"end":468.829,"score":0},{"word":"敵","start":468.829,"end":469.009,"score":0},{"word":"的","start":469.009,"end":469.249,"score":0.021},{"word":"攻","start":469.249,"end":469.629,"score":0},{"word":"擊","start":469.629,"end":470.57,"score":0.004},{"word":"。"},{"word":"世","start":470.57,"end":470.93,"score":0.009},{"word":"界","start":470.93,"end":471.37,"score":0.029},{"word":"對","start":471.37,"end":471.51,"score":0.114},{"word":"我","start":471.51,"end":471.63,"score":0.104},{"word":"們","start":471.63,"end":471.65,"score":0.013},{"word":"的","start":471.65,"end":472.39,"score":0.001},{"word":"這","start":472.39,"end":472.63,"score":0.002},{"word":"種","start":472.63,"end":472.911,"score":0},{"word":"影","start":472.911,"end":473.251,"score":0.001},{"word":"響","start":473.251,"end":473.591,"score":0.004},{"word":"。"},{"word":"主","start":473.591,"end":474.291,"score":0},{"word":"啊","start":474.291,"end":474.431,"score":0},{"word":"祂"},{"word":"們","start":474.431,"end":474.511,"score":0.061},{"word":"要","start":474.511,"end":474.671,"score":0.003},{"word":"把","start":474.671,"end":474.831,"score":0.017},{"word":"我","start":474.831,"end":474.851,"score":0},{"word":"們","start":474.851,"end":475.031,"score":0.103},{"word":"拉","start":475.031,"end":475.332,"score":0.024},{"word":"到","start":475.332,"end":475.972,"score":0.029},{"word":"另","start":475.972,"end":476.112,"score":0.001},{"word":"外","start":476.112,"end":476.232,"score":0},{"word":"一","start":476.232,"end":476.312,"score":0.003},{"word":"個","start":476.312,"end":476.492,"score":0.1},{"word":"方","start":476.492,"end":476.712,"score":0.081},{"word":"向","start":476.712,"end":477.052,"score":0.001},{"word":"去","start":477.052,"end":477.952,"score":0},{"word":"。"},{"word":"主","start":477.952,"end":478.053,"score":0},{"word":"啊","start":478.053,"end":478.173,"score":0},{"word":"有","start":478.173,"end":478.333,"score":0.118},{"word":"時","start":478.333,"end":478.473,"score":0},{"word":"候","start":478.473,"end":478.593,"score":0},{"word":"祂"},{"word":"們","start":478.593,"end":478.673,"score":0.249},{"word":"的","start":478.673,"end":478.873,"score":0.097},{"word":"威","start":478.873,"end":479.053,"score":0.001},{"word":"力","start":479.053,"end":479.213,"score":0.089},{"word":"好","start":479.213,"end":479.533,"score":0.044},{"word":"大","start":479.533,"end":479.713,"score":0},{"word":"啊","start":479.713,"end":480.393,"score":0},{"word":"。"},{"word":"大","start":480.393,"end":480.573,"score":0.068},{"word":"到","start":480.573,"end":480.774,"score":0.015},{"word":"我","start":480.774,"end":480.794,"score":0.05},{"word":"們","start":480.794,"end":480.974,"score":0.019},{"word":"不","start":480.974,"end":481.094,"score":0.153},{"word":"能","start":481.094,"end":481.314,"score":0.079},{"word":"承","start":481.314,"end":481.694,"score":0.003},{"word":"受","start":481.694,"end":482.494,"score":0.01},{"word":"。"},{"word":"但","start":482.494,"end":482.694,"score":0.027},{"word":"是","start":482.694,"end":482.934,"score":0.082},{"word":"主","start":482.934,"end":483.114,"score":0},{"word":"我","start":483.114,"end":483.255,"score":0},{"word":"們","start":483.255,"end":483.695,"score":0.002},{"word":"要","start":483.695,"end":484.075,"score":0.038},{"word":"拼","start":484.075,"end":484.335,"score":0.003},{"word":"死","start":484.335,"end":484.515,"score":0.031},{"word":"命","start":484.515,"end":484.715,"score":0.04},{"word":"的","start":484.715,"end":485.495,"score":0.025},{"word":"抓","start":485.495,"end":485.675,"score":0},{"word":"住","start":485.675,"end":485.876,"score":0.001},{"word":"祢"},{"word":"的","start":485.876,"end":486.136,"score":0.073},{"word":"話","start":486.136,"end":486.396,"score":0.021},{"word":"語","start":486.396,"end":486.956,"score":0},{"word":"。"},{"word":"因","start":486.956,"end":487.096,"score":0.018},{"word":"為","start":487.096,"end":487.176,"score":0.08},{"word":"祢"},{"word":"的","start":487.176,"end":487.256,"score":0.001},{"word":"話","start":487.256,"end":487.736,"score":0},{"word":"語","start":487.736,"end":488.396,"score":0.004},{"word":"。"},{"word":"主","start":488.396,"end":488.517,"score":0.001},{"word":"啊","start":488.517,"end":488.717,"score":0},{"word":"大","start":488.717,"end":488.917,"score":0.09},{"word":"有","start":488.917,"end":489.157,"score":0.071},{"word":"能","start":489.157,"end":489.417,"score":0.037},{"word":"力","start":489.417,"end":490.137,"score":0.009},{"word":"。"},{"word":"祢"},{"word":"的","start":490.137,"end":490.397,"score":0},{"word":"話","start":490.397,"end":490.617,"score":0.008},{"word":"語","start":490.617,"end":490.917,"score":0.011},{"word":"是","start":490.917,"end":491.198,"score":0.068},{"word":"信","start":491.198,"end":491.518,"score":0.011},{"word":"實","start":491.518,"end":491.718,"score":0.014},{"word":"的","start":491.718,"end":491.738,"score":0.601},{"word":"。"}]},{"start":492.398,"end":517.84,"text":"祢的應許的話語,也勝過我們生命中所面對的苦難、誘惑、試探跟攻擊,他們的強度跟他們時間的長度。主啊,我要拼死命,倚靠仰望祢的話語。唯有祢的話語,能把我救活,使我存活。奉主耶穌的名祷告。阿們。願神祝福大家。","words":[{"word":"祢"},{"word":"的","start":492.398,"end":492.978,"score":0},{"word":"應","start":492.978,"end":493.219,"score":0.021},{"word":"許","start":493.219,"end":493.339,"score":0.095},{"word":"的","start":493.339,"end":493.599,"score":0.075},{"word":"話","start":493.599,"end":493.819,"score":0.031},{"word":"語","start":493.819,"end":494.4,"score":0},{"word":","},{"word":"也","start":494.4,"end":494.64,"score":0.082},{"word":"勝","start":494.64,"end":494.98,"score":0},{"word":"過","start":494.98,"end":495.361,"score":0.047},{"word":"我","start":495.361,"end":495.521,"score":0.122},{"word":"們","start":495.521,"end":495.761,"score":0.08},{"word":"生","start":495.761,"end":495.881,"score":0.037},{"word":"命","start":495.881,"end":496.161,"score":0.011},{"word":"中","start":496.161,"end":496.862,"score":0.001},{"word":"所","start":496.862,"end":497.022,"score":0.111},{"word":"面","start":497.022,"end":497.182,"score":0.116},{"word":"對","start":497.182,"end":497.342,"score":0.11},{"word":"的","start":497.342,"end":497.562,"score":0.09},{"word":"苦","start":497.562,"end":497.823,"score":0},{"word":"難","start":497.823,"end":498.643,"score":0.002},{"word":"、"},{"word":"誘","start":498.643,"end":499.104,"score":0},{"word":"惑","start":499.104,"end":499.524,"score":0},{"word":"、"},{"word":"試","start":499.524,"end":499.704,"score":0.001},{"word":"探","start":499.704,"end":499.924,"score":0.004},{"word":"跟","start":499.924,"end":500.165,"score":0.029},{"word":"攻","start":500.165,"end":500.425,"score":0},{"word":"擊","start":500.425,"end":501.025,"score":0},{"word":","},{"word":"他","start":501.025,"end":501.346,"score":0},{"word":"們","start":501.346,"end":501.526,"score":0.109},{"word":"的","start":501.526,"end":501.826,"score":0.034},{"word":"強","start":501.826,"end":502.146,"score":0.008},{"word":"度","start":502.146,"end":502.747,"score":0.004},{"word":"跟","start":502.747,"end":502.907,"score":0.043},{"word":"他","start":502.907,"end":503.067,"score":0.119},{"word":"們","start":503.067,"end":503.247,"score":0},{"word":"時","start":503.247,"end":503.427,"score":0.029},{"word":"間","start":503.427,"end":503.568,"score":0.031},{"word":"的","start":503.568,"end":503.748,"score":0.11},{"word":"長","start":503.748,"end":504.769,"score":0},{"word":"度","start":504.769,"end":504.809,"score":0},{"word":"。"},{"word":"主","start":504.809,"end":505.009,"score":0.002},{"word":"啊","start":505.009,"end":505.149,"score":0},{"word":","},{"word":"我","start":505.149,"end":505.629,"score":0},{"word":"要","start":505.629,"end":506.05,"score":0.04},{"word":"拼","start":506.05,"end":506.33,"score":0.002},{"word":"死","start":506.33,"end":506.53,"score":0.031},{"word":"命","start":506.53,"end":507.251,"score":0.001},{"word":","},{"word":"倚","start":507.251,"end":507.511,"score":0},{"word":"靠","start":507.511,"end":507.871,"score":0},{"word":"仰","start":507.871,"end":507.931,"score":0},{"word":"望","start":507.931,"end":508.632,"score":0},{"word":"祢"},{"word":"的","start":508.632,"end":508.892,"score":0.07},{"word":"話","start":508.892,"end":509.052,"score":0.047},{"word":"語","start":509.052,"end":509.913,"score":0.002},{"word":"。"},{"word":"唯","start":509.913,"end":510.053,"score":0.001},{"word":"有","start":510.053,"end":510.173,"score":0.04},{"word":"祢"},{"word":"的","start":510.173,"end":510.694,"score":0},{"word":"話","start":510.694,"end":510.714,"score":0},{"word":"語","start":510.714,"end":511.294,"score":0},{"word":","},{"word":"能","start":511.294,"end":511.594,"score":0.042},{"word":"把","start":511.594,"end":511.795,"score":0.001},{"word":"我","start":511.795,"end":511.955,"score":0.03},{"word":"救","start":511.955,"end":512.395,"score":0.002},{"word":"活","start":512.395,"end":512.956,"score":0},{"word":","},{"word":"使","start":512.956,"end":513.196,"score":0},{"word":"我","start":513.196,"end":513.396,"score":0.022},{"word":"存","start":513.396,"end":513.476,"score":0.001},{"word":"活","start":513.476,"end":514.357,"score":0},{"word":"。"},{"word":"奉","start":514.357,"end":514.677,"score":0},{"word":"主","start":514.677,"end":514.817,"score":0.001},{"word":"耶","start":514.817,"end":515.037,"score":0},{"word":"穌"},{"word":"的","start":515.037,"end":515.177,"score":0.007},{"word":"名","start":515.177,"end":515.338,"score":0},{"word":"祷"},{"word":"告","start":515.338,"end":515.578,"score":0},{"word":"。"},{"word":"阿","start":515.578,"end":516.318,"score":0},{"word":"們","start":516.318,"end":516.859,"score":0},{"word":"。"},{"word":"願","start":516.859,"end":517.079,"score":0.021},{"word":"神","start":517.079,"end":517.319,"score":0.026},{"word":"祝","start":517.319,"end":517.439,"score":0},{"word":"福","start":517.439,"end":517.579,"score":0.008},{"word":"大","start":517.579,"end":517.82,"score":0.083},{"word":"家","start":517.82,"end":517.84,"score":0.98},{"word":"。"}]}],"language":"zh"}